Workbook

Sheet README
B2: FAMILY OFFICE — ARCHIVO MASTER CONSOLIDADO
B3: Grupo familiar Cristián Armas Morel — preparado a partir de FO.xlsx (jul-2026) y Flujo de Caja (oct-2025)
B5: Perímetro consolidado (decisión del cliente)
B6: Núcleo familiar + hijos: Cristián Armas Morel, Paula Alvear Román, Catalina, Vicente y Tomás Armas Alvear.
B7: Personas vinculadas por sociedad pero fuera del núcleo (yernos/socios externos) se listan aparte en 'Perimetro_Familiar' y no suman al patrimonio neto.
B9: Convenciones de color
B10: Azul = dato de entrada (hardcoded), tomado de un archivo fuente — ver comentario en la celda para la referencia exacta.
B11: Negro = fórmula calculada dentro del archivo.
B12: Verde = fórmula que enlaza a otra pestaña de este mismo archivo.
B13: Amarillo = campo pendiente de completar o supuesto clave que el family office debe validar/ajustar.
B15: Decisiones de diseño acordadas con el cliente
B16: 1) Bienes raíces: se mantienen dos bases en paralelo. El Avalúo Fiscal (SII) alimenta el cálculo de contribuciones en el Flujo de Caja. La Tasación Comercial alimenta la valorización del activo en el Balance; mientras no esté completa, el Balance usa el Avalúo Fiscal como proxy temporal (marcado explícitamente).
... B52: Preparar para: dashboard en vivo vía Codex (lectura directa de este archivo con pandas/openpyxl).

Sheet Supuestos
A1: SUPUESTOS Y PARÁMETROS DEL MODELO
A3: Parámetro | B3: Valor | C3: Nota / Fuente
A4: Fecha de corte — Balance patrimonial (FO.xlsx) | B4: 17-07-2026 | C4: Fecha declarada en FO.xlsx, hoja Resumen
A5: Fecha de corte — Flujo de Caja | B5: 11-10-2025 | C5: Nombre del archivo fuente
A6: Valor UF de referencia (CLP) | B6: 40844.79 | C6: Fuente: Banco Central de Chile, valor al 08-08-2026 (indicadoreschile.cl)
A7: Tipo de cambio USD/CLP de referencia | C7: PENDIENTE — cargar tipo de cambio a la fecha de corte
A8: Factor Tasación Comercial / Avalúo Fiscal (proxy temporal) | B8: 2.35 | C8: Instrucción del cliente (08-2026): mientras no haya tasación real, Tasación Comercial = Avalúo Fiscal x este factor
A9: Inflación anual proyectada (UF) | B9: 0.03 | C9: Supuesto referencial (3,0%) — ajustar según visión del family office
A10: Retorno esperado anual — Liquidez | B10: 0.005 | C10: Supuesto referencial (0,5% real) — cuentas corrientes/efectivo
A11: Retorno esperado anual — Inversiones Financieras | B11: 0.045 | C11: Supuesto referencial (4,5%) — mix renta fija/variable observado en cartera
A12: Retorno esperado anual — Bienes Raíces (plusvalía + arriendo neto) | B12: 0.03 | C12: Supuesto referencial (3,0%) — típico para Santiago/Las Condes, ajustar con tasación real
A13: Retorno esperado anual — Empresas / Equity operativo | B13: 0.06 | C13: Supuesto referencial (6,0%) — mayor riesgo/iliquidez, ajustar con EEFF reales
A14: Tasa de descuento (para VAN si se requiere) | B14: 0.06 | C14: Supuesto referencial
A15: Horizonte KPI 1 | B15: 1 año
A16: Horizonte KPI 2 | B16: 5 años
A17: Horizonte KPI 3 | B17: 10 años

Sheet Perimetro_Familiar
A1: PERÍMETRO FAMILIAR CONSOLIDADO
A2: Decisión del cliente: núcleo + hijos
A4: Persona | B4: RUT | C4: Rol | D4: Vinculación societaria
A5: Cristián Armas Morel | B5: 8.383.601-6 | C5: Cabeza de familia | D5: Vinculado a las 33 empresas (ver pestaña Empresas)
A6: Paula Alvear Román | B6: 8.483.765-2 | C6: Cónyuge | D6: Vinculada a 2 empresas: One Two One S.A., Asesorías e Inversiones Tromen Ltda
A7: Catalina Amalia Armas Alvear | B7: 19.639.061-8 | C7: Hija | D7: Vinculada a 5 empresas: Arbal, Gestora Condominios del Sur, NV SPA, Fractal, Gestora Fractal
A8: Vicente Armas Alvear | B8: 20.755.870-2 | C8: Hijo | D8: Vinculado a 5 empresas: Arbal, Gestora Condominios del Sur, NV SPA, Fractal, Gestora Fractal
A9: Tomás Armas Alvear | B9: 19.244.820-4 | C9: Hijo | D9: Vinculado a 5 empresas: Arbal, Gestora Condominios del Sur, NV SPA, Fractal, Gestora Fractal
A11: Fuera del perímetro (vinculados por sociedad, no consolidan)
A12: Persona | B12: RUT | C12: Nota
A13: Gerardo Balbontín Pérez | B13: 19.245.356-9 | C13: Vinculado por Arbal Constructora SPA — fuera del núcleo definido
A14: Andrés Gerardo Croquevielle Bustamante | B14: 16.795.208-9 | C14: Vinculado por Gestora Fractal SPA — fuera del núcleo definido
A15: Félix Javier Escudero Fernández | B15: 17.082.540-3 | C15: Vinculado por Gestora Fractal SPA — fuera del núcleo definido

Sheet Liquidez
A1: LIQUIDEZ
A2: Fuente principal: Flujo de Caja (detalle operacional, oct-2025). Bloque FO.xlsx (jul-2026) como referencia — NO se suma al total para evitar doble conteo.
A4: Cuenta / Plataforma | B4: Titular / Entidad | C4: Perímetro | D4: Monto (CLP) | E4: Nota
A5: Cta Cte Banco Estado CAM | B5: Cristián Armas Morel | C5: Familia | D5: 1016519
A6: Cta Cte Banco Estado Paula | B6: Paula Alvear Román | C6: Familia | D6: 7335
A7: Cta Cte Bipersonal BICE | B7: Cristián Armas Morel / Paula Alvear (cuenta conjunta) | C7: Familia | D7: 9625060
A8: Cta Cte BICE Paula | B8: Paula Alvear Román | C8: Familia | D8: 0
A9: Cta Cte Falabella Carola | B9: Carola (fuera de núcleo familiar) | C9: Fuera | D9: 61649
A10: Cta Cte Santander G3 | B10: Inversiones y Rentas G3 SPA | C10: Empresa | D10: 0
A11: Cta Cte Consorcio G3 | B11: Inversiones y Rentas G3 SPA | C11: Empresa | D11: 4572849
A12: Cta Cte BICE NV | B12: NV SPA | C12: Empresa | D12: 20395034
A13: Cta Cte Chile CAM 8470188801 | B13: Cristián Armas Morel | C13: Familia | D13: 0
A14: Cta Cte Chile Praga | B14: Praga S.A. | C14: Empresa | D14: 18000000
A15: Cta Cte Santander Cristián 1 | B15: Cristián Armas Morel | C15: Familia | D15: 264000
A16: Cta Cte Santander Cristián 2 | B16: Cristián Armas Morel | C16: Familia | D16: 1032
... A31: Vales Vista | B31: Familia | C31: Familia | D31: 0
A32: SUBTOTAL LIQUIDEZ (Flujo de Caja, perímetro completo) | D32: =SUM(D5:D31) -> 121090932
A33: SUBTOTAL LIQUIDEZ (solo perímetro núcleo+hijos, excluye 'Fuera' y 'Empresa') | D33: =SUMIF(C5:C31,"Familia",D5:D31) -> 46044820
A35: REFERENCIA — FO.xlsx (jul-2026), no incluida en el subtotal de arriba
A36: Plataforma | B36: Titular | D36: Monto (CLP) | E36: Nota
A37: Tenpo | B37: Cristián Armas Morel | D37: 14828776
A38: Mercado Pago | B38: Cristián Armas Morel | D38: 10052183
A39: Copec Pay | B39: Cristián Armas Morel | D39: 19726835
A40: Mach | B40: Cristián Armas Morel | D40: 24902364
A41: Cuenta RUT | B41: Paula Alvear Román | D41: 229527
A42: Fintual Reserva | B42: Cristián Armas Morel | D42: 179700
A43: Total FO.xlsx (referencia) | D43: =SUM(D37:D42) -> 69919385

Sheet Inversiones_Financieras
A1: INVERSIONES FINANCIERAS
A2: Fuente principal: Flujo de Caja (oct-2025). Bloque FO.xlsx (jul-2026) como referencia — NO se suma al total.
A4: Instrumento | B4: Titular / Entidad | C4: Perímetro | D4: Monto (CLP) | E4: Nota
A5: Acciones Polo | B5: Paula Alvear Román | C5: Familia | D5: 11000000 | E5: Custodia Club de Polo a nombre de Paula
A6: Bell Air | B6: NV SPA | C6: Empresa | D6: 114800000 | E6: Filial de NV en USA, administrada por Boris Buvinic
A7: Citify | B7: Paula Alvear Román | C7: Familia | D7: 33000000 | E7: Acciones privadas - Citify.cl
A8: APV Cristián Habitat | B8: Cristián Armas Morel | C8: Familia | D8: 9001000 | E8: Ahorro previsional voluntario
A9: Casa Nuba | B9: NV SPA (filial NV Punta de Lobos) | C9: Empresa | D9: 2424352 | E9: Discrepancia de magnitud vs. pestaña 'Resumen Inversiones' - verificar
A10: Capital Office | B10: Capital Office SPA | C10: Empresa | D10: 0
A11: Dólares BICE Paula | B11: Paula Alvear Román | C11: Familia | D11: 602227 | E11: Posición en USD
A12: Fraccional | B12: Cristián Armas Morel | C12: Familia | D12: 331000 | E12: Inversión inmobiliaria fraccionada
A13: FM BICE Paula | B13: Paula Alvear Román | C13: Familia | D13: 127137377 | E13: Fondo mutuo
A14: FM Banco Estado Cristián | B14: Cristián Armas Morel | C14: Familia | D14: 2530189 | E14: Fondo mutuo
A15: FM Banco Estado Paula | B15: Paula Alvear Román | C15: Familia | D15: 227000 | E15: Fondo mutuo
A16: FM BICE CAM | B16: Cristián Armas Morel | C16: Familia | D16: 130497907 | E16: Fondo mutuo
A17: FM Santander DL | B17: Sin identificar ("DL") — verificar (monto material) | C17: Pendiente | D17: 834889277 | E17: Requiere identificación prioritaria antes de consolidar
A18: FM Falabella Carola | B18: Carola (fuera de núcleo familiar) | C18: Fuera | D18: 46102759
A19: FM Falabella Paula | B19: Paula Alvear Román | C19: Familia | D19: 5000200 | E19: Fondo mutuo
A20: FM Santander G3 | B20: Inversiones y Rentas G3 SPA | C20: Empresa | D20: 33869908 | E20: Fondo mutuo
A21: BTG Paula | B21: Paula Alvear Román | C21: Familia | D21: 0
A22: BTG Cristián | B22: Cristián Armas Morel | C22: Familia | D22: 0
A23: Vantrust Cristián | B23: Cristián Armas Morel | C23: Familia | D23: 0
A24: Credicorp Paula | B24: Paula Alvear Román | C24: Familia | D24: 0
A25: Credicorp Cristián | B25: Cristián Armas Morel | C25: Familia | D25: 0
A26: FM BICE Design | B26: Design Apart SPA | C26: Empresa | D26: 198000000 | E26: Fondo mutuo
A27: FM NV BICE | B27: NV SPA | C27: Empresa | D27: 68985812 | E27: Fondo mutuo
A28: FM Santander Paula | B28: Paula Alvear Román | C28: Familia | D28: 12869153 | E28: Fondo mutuo
A29: FM Santander Cristián | B29: Cristián Armas Morel | C29: Familia | D29: 31287000 | E29: Fondo mutuo
A30: FM Banchile Praga | B30: Praga S.A. | C30: Empresa | D30: 111896190 | E30: Fondo mutuo
A31: FM Security Paula (Claudio Sedán) | B31: Paula Alvear Román | C31: Familia | D31: 22413824 | E31: Fondo mutuo, ejecutivo Claudio Sedán
A32: Cryptomarket Cristián | B32: Cristián Armas Morel | C32: Familia | D32: 104195 | E32: Criptoactivos
A33: Saldo Habitat Fondo de Pensión Paula | B33: Paula Alvear Román | C33: Familia | D33: 692208 | E33: Previsional
A34: Cta Dólares C.Taverne Cristián | B34: Cristián Armas Morel | C34: Familia | D34: 64823142 | E34: USD
A35: Cta Dólares C.Taverne Paula | B35: Paula Alvear Román | C35: Familia | D35: 2291596 | E35: USD
A36: Collins Park, Texas (USA) | B36: Cristián Armas Morel (asumido — confirmar titular) | C36: Familia | D36: =150000*913.86 -> 137079000 | E36: Fuente: dato entregado por el cliente (08-2026), no figuraba en FO.xlsx ni en el Flujo de Caja. USD 150.000 x $913.86 (Dólar Observado, Banco Central de Chile, 08-08-2026).
A37: SUBTOTAL INVERSIONES FINANCIERAS (Flujo de Caja, perímetro completo) | D37: =SUM(D5:D36) -> 2001855316
A38: SUBTOTAL INVERSIONES FINANCIERAS (solo perímetro núcleo+hijos) | D38: =SUMIF(C5:C36,"Familia",D5:D36) -> 590887018
A40: REFERENCIA — FO.xlsx (jul-2026), no incluida en el subtotal de arriba
A41: Institución / Instrumento | B41: Titular | C41: Monto (CLP) | D41: Nota
A42: BICE Inversiones — Renta Largo Plazo | B42: Cristián Armas Morel | C42: 29341138
A43: BICE Inversiones — Renta a Largo Plazo | B43: Cristián Armas Morel | C43: 138427987
A44: BICE Inversiones — Renta UF | B44: Cristián Armas Morel | C44: 17906187
A45: BICE Inversiones — Renta UF | B45: Cristián Armas Morel | C45: 26380233
A46: BICE Inversiones — Acciones Chile Activo | B46: Cristián Armas Morel | C46: 1975623
A47: AFP Habitat — Ahorro Previsional (Fondo de Pensión) | B47: Cristián Armas Morel | C47: 9041282
A48: BICE Digital — Acciones Chile Activo | B48: Paula Alvear Román | C48: 15289310
A49: BICE Inversiones — Renta Largo Plazo | B49: Paula Alvear Román | C49: 12133240
A50: BICE Inversiones — Renta Largo Plazo | B50: Paula Alvear Román | C50: 29409681
A51: BICE Inversiones — Renta UF | B51: Paula Alvear Román | C51: 5196
A52: Banco Estado — Fondo Mutuo Conservador | B52: Cristián Armas Morel | C52: 7316362
A53: Banco Estado — Inversión (detalle pendiente) | B53: Paula Alvear Román | C53: 9173229
... A58: Santander — Tesorería Digital | B58: Cristián Armas Morel | C58: 709110
A59: Total FO.xlsx (referencia) | C59: =SUM(C42:C58) -> 352014831

Sheet Otras_Partidas
A1: OTRAS PARTIDAS — PROVISIONES, CUENTAS POR COBRAR OPERACIONALES Y MENORES
A2: Fuente: Flujo de Caja, oct-2025 (miles → convertido a pesos). No forman parte del Patrimonio Neto principal salvo Cuentas por Cobrar operacionales, que sí se incluyen.
A4: Provisiones (fondos reservados — contra-activo)
A5: Concepto | B5: Monto (CLP)
A6: Provisión pago factoring Pedro Schain | B6: -45000000
A7: Provisión arreglos Casa Santuario | B7: -80000000
A8: Provisión de impuestos | B8: -50000000
A9: Provisión hospitalizaciones | B9: -90000000
A10: Subtotal — no incluida en Patrimonio Neto (memo) | B10: =SUM(B6:B9) -> -265000000
A12: Cuentas por cobrar operacionales
A13: Concepto | B13: Monto (CLP)
A14: Cuentas por cobrar departamentos | B14: 100000
A15: Meme por cobrar a Rodrigo Fuenzalida (arriendo Itaú Meme 40%) | B15: 0
A16: Pensiones por cobrar Paula y Cristián | B16: 990000
A17: Saldo Francisca Velasco | B17: 0
A18: Seguro de cesantía Paula por cobrar | B18: 3735175
A19: Varios por cobrar | B19: 0
A20: Pagos anticipados, dividendos casa, etc. | B20: 75252065
A21: Subtotal — SÍ incluida en Activos | B21: =SUM(B14:B20) -> 80077240
A23: Otros activos menores (puntos, mausoleo, etc.)
A24: Concepto | B24: Monto (CLP)
A25: Puntos Falabella Paula (Banco) | B25: 15456
A26: Puntos Falabella Paula (CMR) | B26: 155456
A27: Puntos Falabella Cristián (Banco) | B27: 54
A28: Puntos Falabella Carola (Banco) | B28: 4672
A29: Matrimonios (provisión evento) | B29: 0
A30: Tumba Zapallar | B30: 39000000
A31: Subtotal — SÍ incluida en Activos | B31: =SUM(B25:B30) -> 39175638

Sheet Bienes_Raices
A1: BIENES RAÍCES — 28 PROPIEDADES
A2: Avalúo Fiscal alimenta el cálculo de contribuciones (Flujo de Caja). Tasación Comercial alimenta el Balance. Mientras no haya tasación real, se usa como proxy: Avalúo Fiscal x factor (pestaña Supuestos, hoy 2,35x, instrucción del cliente 08-2026). 'Valor Atribuible' pondera por el % de participación de la familia en cada activo (por defecto 100%, salvo indicación contraria).
A4: ID | B4: Tipo | C4: Dirección | D4: Comuna | E4: Rol SII | F4: Sup. (m²) | G4: Titular | H4: Avalúo Fiscal (CLP) | I4: Tasación Comercial (CLP) | J4: % Participación | K4: Valor Balance (CLP) | L4: Valor Atribuible (CLP) | M4: Fuente valor usado | N4: año compra
A5: 1 | B5: Departamento | C5: Apoquindo 6498, Unidad 702 (A) | D5: Las Condes | E5: 1533-30 | F5: 101 | G5: Praga | H5: 225007612 | J5: 0.5 | K5: =IF(I5>0,I5,IF(H5>0,H5*Supuestos!$B$8,0)) -> 5.2876789e+08 | L5: =K5*J5 -> 2.6438394e+08 | M5: =IF(I5>0,"Tasación directa/comercial",IF(H5>0,"Avalúo Fiscal x factor (proxy)","PENDIENTE — sin dato")) -> Avalúo Fiscal x factor (proxy)
A6: 2 | B6: Oficina | C6: Apoquindo 5701 | D6: Las Condes | E6: 567-47 | F6: 26 | G6: Praga | H6: 42065479 | J6: 0.5 | K6: =IF(I6>0,I6,IF(H6>0,H6*Supuestos!$B$8,0)) -> 98853876 | L6: =K6*J6 -> 49426938 | M6: =IF(I6>0,"Tasación directa/comercial",IF(H6>0,"Avalúo Fiscal x factor (proxy)","PENDIENTE — sin dato")) -> Avalúo Fiscal x factor (proxy)
A7: 3 | B7: Casa | C7: Warren Smith 32 | D7: Las Condes | E7: 667-44 | F7: 120 | G7: Praga | H7: 208548956 | J7: 0.5 | K7: =IF(I7>0,I7,IF(H7>0,H7*Supuestos!$B$8,0)) -> 4.9009005e+08 | L7: =K7*J7 -> 2.4504502e+08 | M7: =IF(I7>0,"Tasación directa/comercial",IF(H7>0,"Avalúo Fiscal x factor (proxy)","PENDIENTE — sin dato")) -> Avalúo Fiscal x factor (proxy)
A8: 4 | B8: Casa | C8: Warren Smith 15 | D8: Las Condes | E8: 683-1 | F8: 120 | G8: Praga | H8: 312178031 | J8: 0.5 | K8: =IF(I8>0,I8,IF(H8>0,H8*Supuestos!$B$8,0)) -> 7.3361837e+08 | L8: =K8*J8 -> 3.6680919e+08 | M8: =IF(I8>0,"Tasación directa/comercial",IF(H8>0,"Avalúo Fiscal x factor (proxy)","PENDIENTE — sin dato")) -> Avalúo Fiscal x factor (proxy)
A9: 5 | B9: Casa | C9: Rosario Norte 33 | D9: Las Condes | E9: 715-58 | F9: 110 | G9: Praga | H9: 202860587 | J9: 0.5 | K9: =IF(I9>0,I9,IF(H9>0,H9*Supuestos!$B$8,0)) -> 4.7672238e+08 | L9: =K9*J9 -> 2.3836119e+08 | M9: =IF(I9>0,"Tasación directa/comercial",IF(H9>0,"Avalúo Fiscal x factor (proxy)","PENDIENTE — sin dato")) -> Avalúo Fiscal x factor (proxy)
A10: 6 | B10: Casa | C10: Rosario Norte 41 | D10: Las Condes | E10: 715-72 | F10: 110 | G10: Praga | H10: 198838652 | J10: 0.5 | K10: =IF(I10>0,I10,IF(H10>0,H10*Supuestos!$B$8,0)) -> 4.6727083e+08 | L10: =K10*J10 -> 2.3363542e+08 | M10: =IF(I10>0,"Tasación directa/comercial",IF(H10>0,"Avalúo Fiscal x factor (proxy)","PENDIENTE — sin dato")) -> Avalúo Fiscal x factor (proxy)
A11: 7 | B11: Oficina | C11: Las Condes 10465, Unidad Ofc 717 ps7 edificio | D11: Las Condes | E11: 2472-417 | F11: 48 | G11: NV | H11: 66899039 | J11: 1 | K11: =IF(I11>0,I11,IF(H11>0,H11*Supuestos!$B$8,0)) -> 1.5721274e+08 | L11: =K11*J11 -> 1.5721274e+08 | M11: =IF(I11>0,"Tasación directa/comercial",IF(H11>0,"Avalúo Fiscal x factor (proxy)","PENDIENTE — sin dato")) -> Avalúo Fiscal x factor (proxy)
A12: 8 | B12: Local Comercial | C12: Colón 5923, Unidad L 10 | D12: Las Condes | E12: 726-78 | F12: 26 | G12: Cristián Armas & Paula Alvear | H12: 91434415 | J12: 0.5 | K12: =IF(I12>0,I12,IF(H12>0,H12*Supuestos!$B$8,0)) -> 2.1487088e+08 | L12: =K12*J12 -> 1.0743544e+08 | M12: =IF(I12>0,"Tasación directa/comercial",IF(H12>0,"Avalúo Fiscal x factor (proxy)","PENDIENTE — sin dato")) -> Avalúo Fiscal x factor (proxy)
A13: 9 | B13: Local Comercial | C13: Colón 5911, Unidad L 12-A | D13: Las Condes | E13: 726-81 | F13: 26 | G13: Cristián Armas & Paula Alvear | H13: 91434415 | J13: 0.5 | K13: =IF(I13>0,I13,IF(H13>0,H13*Supuestos!$B$8,0)) -> 2.1487088e+08 | L13: =K13*J13 -> 1.0743544e+08 | M13: =IF(I13>0,"Tasación directa/comercial",IF(H13>0,"Avalúo Fiscal x factor (proxy)","PENDIENTE — sin dato")) -> Avalúo Fiscal x factor (proxy)
A14: 10 | B14: Local Comercial | C14: La Capitanía 1014, Unidad L 16 | D14: Las Condes | E14: 726-84 | F14: 26 | G14: Cristián Armas & Paula Alvear | H14: 71318577 | J14: 0.5 | K14: =IF(I14>0,I14,IF(H14>0,H14*Supuestos!$B$8,0)) -> 1.6759866e+08 | L14: =K14*J14 -> 83799328 | M14: =IF(I14>0,"Tasación directa/comercial",IF(H14>0,"Avalúo Fiscal x factor (proxy)","PENDIENTE — sin dato")) -> Avalúo Fiscal x factor (proxy)
A15: 11 | B15: Departamento | C15: JJ Prieto 4260, Unidad 208 | D15: San Miguel | E15: 3865-107 | F15: 54.63 | G15: NV | H15: 57729170 | J15: 1 | K15: =IF(I15>0,I15,IF(H15>0,H15*Supuestos!$B$8,0)) -> 1.3566355e+08 | L15: =K15*J15 -> 1.3566355e+08 | M15: =IF(I15>0,"Tasación directa/comercial",IF(H15>0,"Avalúo Fiscal x factor (proxy)","PENDIENTE — sin dato")) -> Avalúo Fiscal x factor (proxy)
A16: 12 | B16: Departamento | C16: JJ Prieto 4260, Unidad 308 | D16: San Miguel | E16: 3865-123 | F16: 54.63 | G16: NV | H16: 57729170 | J16: 1 | K16: =IF(I16>0,I16,IF(H16>0,H16*Supuestos!$B$8,0)) -> 1.3566355e+08 | L16: =K16*J16 -> 1.3566355e+08 | M16: =IF(I16>0,"Tasación directa/comercial",IF(H16>0,"Avalúo Fiscal x factor (proxy)","PENDIENTE — sin dato")) -> Avalúo Fiscal x factor (proxy)
... A30: 26 | B30: Departamento | C30: Mario Kreutzberger 1520, Unidad 2308A | D30: Santiago | E30: 1216-322 | F30: 26.92 | G30: FO | H30: 44663594 | J30: 1 | K30: =IF(I30>0,I30,IF(H30>0,H30*Supuestos!$B$8,0)) -> 1.0495945e+08 | L30: =K30*J30 -> 1.0495945e+08 | M30: =IF(I30>0,"Tasación directa/comercial",IF(H30>0,"Avalúo Fiscal x factor (proxy)","PENDIENTE — sin dato")) -> Avalúo Fiscal x factor (proxy)
B31: Departamento | C31: La cabaña | D31: Lo Barnechea | G31: MEME spa | J31: 1
A32: 27 | B32: Casa | C32: Casa Santuario (dirección pendiente de confirmar) | D32: Pendiente | E32: Pendiente | F32: 730 | G32: San Salvador | I32: 2042239500 | J32: 1 | K32: =IF(I32>0,I32,IF(H32>0,H32*Supuestos!$B$8,0)) -> 2042239500 | L32: =K32*J32 -> 2042239500 | M32: =IF(I32>0,"Tasación directa/comercial",IF(H32>0,"Avalúo Fiscal x factor (proxy)","PENDIENTE — sin dato")) -> Tasación directa/comercial
A33: 28 | B33: Local Comercial | C33: Local Av. La dehesa | D33: Lo barnechea | E33: Pendiente | G33: MEME spa | I33: =9000000*12/0.055 -> 1.9636364e+09 | J33: 0.4 | K33: =IF(I33>0,I33,IF(H33>0,H33*Supuestos!$B$8,0)) -> 1.9636364e+09 | L33: =K33*J33 -> 7.8545455e+08 | M33: =IF(I33>0,"Tasación directa/comercial",IF(H33>0,"Avalúo Fiscal x factor (proxy)","PENDIENTE — sin dato")) -> Tasación directa/comercial
B34: departamento | C34: tajamar con encomenderos | D34: Las Condes | I34: =18000*40850 -> 735300000 | J34: 0.089 | K34: =IF(I34>0,I34,IF(H34>0,H34*Supuestos!$B$8,0)) -> 735300000 | L34: =K34*J34 -> 65441700
B36: Lotes Cementerio | C36: Cementerio Zapallar | D36: Zapallar | E36: Lote 12 | G36: Cristian armas & Paula Alvear | I36: 33000000
B37: Casa Nuba PL | C37: Pichilemu av. Punta lobos | G37: NV Punta Lobos | I37: 800000000 | J37: 0.5
A38: 29 | B38: Strip Center | C38: Strip Center Machalí (dirección pendiente de confirmar) | D38: Machalí | E38: Pendiente | G38: NV | I38: =1100000000/0.4 -> 2750000000 | J38: 0.35 | K38: =IF(I38>0,I38,IF(H38>0,H38*Supuestos!$B$8,0)) -> 2750000000 | L38: =K38*J38 -> 9.625e+08 | M38: =IF(I38>0,"Tasación directa/comercial",IF(H38>0,"Avalúo Fiscal x factor (proxy)","PENDIENTE — sin dato")) -> Tasación directa/comercial
G39: TOTAL | H39: =SUM(H5:H38) -> 2086813271 | I39: =SUM(I5:I38) -> 8.3241759e+09 | K39: =SUM(K5:K38) -> 1.2395187e+10 | L39: =SUM(L5:L38) -> 7.063315e+09

Sheet Empresas
A1: EMPRESAS Y PARTICIPACIONES SOCIETARIAS
A2: Decisión del cliente: estimar equity value con los % 'a verificar' como provisorios. Patrimonio contable no disponible en la mayoría de las empresas — celda de entrada en amarillo. EASA (fila nueva, 08-2026) sí trae % y valoración entregados por el cliente.
A4: Empresa | B4: RUT | C4: % Participación (provisorio) | D4: Patrimonio Contable (CLP) | E4: Equity Value Estimado (CLP) | F4: Nota
A5: Capital Office SPA | B5: 76.076.775-1 | C5: 0.3 | D5: =330000000*3.3 -> 1089000000 | E5: =IF(AND(C5<>"",D5<>""),C5*D5,0) -> 326700000 | F5: % sin ningún valor (ni provisorio)
A6: Inmobiliaria Miraflores Chillán SPA | B6: 76.536.364-0 | C6: 0.5 | E6: =IF(AND(C6<>"",D6<>""),C6*D6,0) -> 0
A7: Constructora de Viviendas Sociales SPA | B7: 76.528.939-4 | C7: 0.5 | E7: =IF(AND(C7<>"",D7<>""),C7*D7,0) -> 0
A8: Sociedad Importadora y Exportadora One Two One S.A. | B8: 76.104.016-2 | E8: =IF(AND(C8<>"",D8<>""),C8*D8,0) -> 0 | F8: % sin ningún valor (ni provisorio)
A9: Asesorías Inversiones y Eventos Cam SPA | B9: 76.258.861-7 | E9: =IF(AND(C9<>"",D9<>""),C9*D9,0) -> 0 | F9: % sin ningún valor (ni provisorio)
A10: Inmobiliaria Nueva Vida SPA | B10: 76.440.017-8 | E10: =IF(AND(C10<>"",D10<>""),C10*D10,0) -> 0 | F10: % sin ningún valor (ni provisorio)
A11: Inmobiliaria El Encanto de Santa Cruz SPA | B11: 76.692.967-2 | E11: =IF(AND(C11<>"",D11<>""),C11*D11,0) -> 0 | F11: % sin ningún valor (ni provisorio)
A12: Ainspecciona SPA | B12: 78.362.551-2 | C12: 0.45 | E12: =IF(AND(C12<>"",D12<>""),C12*D12,0) -> 0
A13: Inmobiliaria y Constructora Evolution SPA | B13: 76.349.697-K | E13: =IF(AND(C13<>"",D13<>""),C13*D13,0) -> 0 | F13: % sin ningún valor (ni provisorio)
A14: Inversiones San Salvador SPA | B14: 77.608.045-4 | E14: =IF(AND(C14<>"",D14<>""),C14*D14,0) -> 0 | F14: % sin ningún valor (ni provisorio)
A15: Constructora Armas Mariategui SPA | B15: 76.131.678-8 | C15: 0.8 | E15: =IF(AND(C15<>"",D15<>""),C15*D15,0) -> 0
A16: Constructora Armas Serrano SPA | B16: 76.134.683-0 | E16: =IF(AND(C16<>"",D16<>""),C16*D16,0) -> 0 | F16: % sin ningún valor (ni provisorio)
A17: Consultora Gan Limitada | B17: 76.693.129-4 | E17: =IF(AND(C17<>"",D17<>""),C17*D17,0) -> 0 | F17: % sin ningún valor (ni provisorio)
A18: Asesorías e Inversiones Tromen Limitada | B18: 77.362.530-1 | E18: =IF(AND(C18<>"",D18<>""),C18*D18,0) -> 0 | F18: % sin ningún valor (ni provisorio)
A19: Dos Mas Dos S.A. | B19: 76.065.942-8 | C19: 0.001 | E19: =IF(AND(C19<>"",D19<>""),C19*D19,0) -> 0
A20: Inversiones y Rentas Aspid SPA | B20: 76.656.130-6 | C20: 0.005 | E20: =IF(AND(C20<>"",D20<>""),C20*D20,0) -> 0
A21: Constructora Armas San Francisco SPA | B21: 76.131.684-2 | E21: =IF(AND(C21<>"",D21<>""),C21*D21,0) -> 0 | F21: % sin ningún valor (ni provisorio)
A22: Constructora Armas Las Condes SPA | B22: 76.123.575-3 | E22: =IF(AND(C22<>"",D22<>""),C22*D22,0) -> 0 | F22: % sin ningún valor (ni provisorio)
A23: Arbal Constructora y Servicios de Marketing SPA | B23: 77.194.209-1 | E23: =IF(AND(C23<>"",D23<>""),C23*D23,0) -> 0 | F23: % sin ningún valor (ni provisorio)
A24: Gestora Condominios del Sur SPA | B24: 77.194.212-1 | E24: =IF(AND(C24<>"",D24<>""),C24*D24,0) -> 0 | F24: % sin ningún valor (ni provisorio)
A25: Inversiones Gan SPA | B25: 76.098.805-7 | E25: =IF(AND(C25<>"",D25<>""),C25*D25,0) -> 0 | F25: % sin ningún valor (ni provisorio)
A26: Transportes Armas Limitada | B26: 78.443.540-7 | C26: 1 | E26: =IF(AND(C26<>"",D26<>""),C26*D26,0) -> 0
A27: NV SPA | B27: 76.118.628-0 | E27: =IF(AND(C27<>"",D27<>""),C27*D27,0) -> 0 | F27: % sin ningún valor (ni provisorio)
A28: Fractal Constructora y Servicios de Marketing SPA | B28: 77.371.647-1 | E28: =IF(AND(C28<>"",D28<>""),C28*D28,0) -> 0 | F28: % sin ningún valor (ni provisorio)
A29: Inversiones Alborada SPA | B29: 77.608.056-K | C29: 1 | E29: =IF(AND(C29<>"",D29<>""),C29*D29,0) -> 0
A30: Asesorías e Inversiones Akron SPA | B30: 76.014.097-K | C30: 0.5 | E30: =IF(AND(C30<>"",D30<>""),C30*D30,0) -> 0
A31: Constructora Armas Cerro Colorado SPA | B31: 76.131.676-1 | C31: 1 | E31: =IF(AND(C31<>"",D31<>""),C31*D31,0) -> 0
A32: Inversiones San Benito SPA | B32: 77.608.053-5 | E32: =IF(AND(C32<>"",D32<>""),C32*D32,0) -> 0 | F32: % sin ningún valor (ni provisorio)
A33: Capellanía Capacitación Limitada | B33: 76.162.368-0 | E33: =IF(AND(C33<>"",D33<>""),C33*D33,0) -> 0 | F33: % sin ningún valor (ni provisorio)
A34: Gestora Fractal SPA | B34: 77.371.646-3 | E34: =IF(AND(C34<>"",D34<>""),C34*D34,0) -> 0 | F34: % sin ningún valor (ni provisorio)
A35: Constructora Armas Padre Mariano SPA | B35: 76.131.682-6 | E35: =IF(AND(C35<>"",D35<>""),C35*D35,0) -> 0 | F35: % sin ningún valor (ni provisorio)
A36: Design Apart SPA | B36: 76.359.867-5 | E36: =IF(AND(C36<>"",D36<>""),C36*D36,0) -> 0 | F36: % sin ningún valor (ni provisorio)
A37: Inmob Armas Irarrazaval Ltda | B37: 76.803.240-8 | C37: 1 | E37: =IF(AND(C37<>"",D37<>""),C37*D37,0) -> 0
A38: Empresas Armas S.A. (EASA) | B38: Pendiente de confirmar | C38: 0.19 | D38: =6500000000/0.19 -> 3.4210526e+10 | E38: =IF(AND(C38<>"",D38<>""),C38*D38,0) -> 6500000000 | F38: EASA (08-2026): RUT pendiente de confirmar. El cliente confirmó que $6.500.000.000 corresponde al valor de su 19% de participación.
A39: TOTAL EQUITY VALUE ESTIMADO (34 empresas) | E39: =SUM(E5:E38) -> 6826700000

Sheet Pasivos
A1: PASIVOS — PATENTES COMERCIALES MOROSAS
A2: Único pasivo formal identificado en las fuentes con monto cierto y exigible. Las deudas personales en disputa se tratan como Activos Contingentes (ver pestaña respectiva), no como pasivo.
A4: RUT | B4: Empresa | C4: Comuna | D4: Deuda (CLP) | E4: Nota
A5: 76.409.354-2 | B5: Interbodegas SPA | C5: Las Condes | D5: 373841
A6: 76.118.628-0 | B6: NV SPA | C6: Recoleta | D6: 8673561
A7: 76.239.590-8 | B7: Inversiones Meme Ltda | C7: Recoleta | D7: 35025
A8: 76.379.167-K | B8: Inversiones y Rentas G3 SPA | C8: Las Condes | D8: 592649
A9: 78.734.530-1 | B9: Praga S.A. | C9: Zapallar | D9: 2066998 | E9: Nota: PRAGA S.A. figura con nota del archivo original: pago 28-12-2023 a Municipalidad de Zapallar aún no confirmado por el municipio.
B10: TOTAL PASIVOS | D10: =SUM(D5:D9) -> 11742074
A12: Nota: otras 8 sociedades del registro de patentes no muestran deuda ('No registra deuda / no tiene patente') y no se incluyen arriba.
A13: Nota: varias de las empresas con deuda de patentes no figuran en el listado de 33 empresas de la pestaña 'Empresas' — registro societario incompleto, requiere conciliación.

Sheet Activos_Contingentes
A1: ACTIVOS CONTINGENTES — CUENTAS POR COBRAR EN DISPUTA / LITIGIO
A2: Corrección importante: en el archivo Flujo de Caja estas 3 líneas están dentro del bloque de ACTIVOS (fila 83, 'Total Activos'), es decir son montos que la familia podría recuperar — no deudas que la familia deba pagar. Se excluyen del Patrimonio Neto principal por su carácter incierto/judicial, y se muestran aparte para trazabilidad.
A4: Concepto | B4: Monto (CLP) | C4: Estado / Nota
A5: Deuda María José Gamboa | B5: 12662913 | C5: Cuenta por cobrar en gestión de cobranza
A6: Deuda Luna | B6: 161272850 | C6: En proceso penal — recuperación sujeta a resultado judicial
A7: Deuda Germán Fidel Oteiza | B7: 7000000 | C7: Cuenta por cobrar
A8: TOTAL ACTIVOS CONTINGENTES (memo, fuera del Patrimonio Neto principal) | B8: =SUM(B5:B7) -> 180935763

Sheet Flujo_Caja
A1: FLUJO DE CAJA — DETALLE MENSUAL HORIZONTAL (AGO-26 A JUL-31, 60 MESES) | B1: 40850
A2: Fuente: Flujo_de_Caja...OCTUBRE_2025.xlsx, hoja 'Flujo General' (miles → convertido a pesos). Ventana: desde el mes más cercano a hoy (ago-2026) hasta 5 años después (jul-2031). Todas las líneas de ingreso y costo del modelo original, mes a mes.
A4: Concepto | B4: ago-26 | C4: sep-26 | D4: oct-26 | E4: nov-26 | F4: dic-26 | G4: ene-27 | H4: feb-27 | I4: mar-27 | J4: abr-27 | K4: may-27 | L4: jun-27 | M4: jul-27 | N4: ago-27 | O4: sep-27 | P4: oct-27 | Q4: nov-27 | R4: dic-27 | S4: ene-28 | T4: feb-28 | U4: mar-28 | V4: abr-28 | W4: may-28 | X4: jun-28 | Y4: jul-28 | Z4: ago-28 | AA4: sep-28 | AB4: oct-28 | AC4: nov-28 | AD4: dic-28 | AE4: ene-29 | AF4: feb-29 | AG4: mar-29 | AH4: abr-29 | AI4: may-29 | AJ4: jun-29 | AK4: jul-29 | AL4: ago-29 | AM4: sep-29 | AN4: oct-29 | AO4: nov-29 | AP4: dic-29 | AQ4: ene-30 | AR4: feb-30 | AS4: mar-30 | AT4: abr-30 | AU4: may-30 | AV4: jun-30 | AW4: jul-30 | AX4: ago-30 | AY4: sep-30 | AZ4: oct-30 | BA4: nov-30 | BB4: dic-30 | BC4: ene-31 | BD4: feb-31 | BE4: mar-31 | BF4: abr-31 | BG4: may-31 | BH4: jun-31 | BI4: jul-31
A5: INGRESOS
A6: PENSIONES (UF) | B6: =1670000+965000 -> 2635000 | C6: 2739616 | D6: 2739616 | E6: 2739616 | F6: 2739616 | G6: 2739616 | H6: 2739616 | I6: 2739616 | J6: 2739616 | K6: 2739616 | L6: 2739616 | M6: 2739616 | N6: 2739616 | O6: 2739616 | P6: 2739616 | Q6: 2739616 | R6: 2739616 | S6: 2739616 | T6: 2739616 | U6: 2739616 | V6: 2739616 | W6: 2739616 | X6: 2739616 | Y6: 2739616 | Z6: 2739616 | AA6: 2739616 | AB6: 2739616 | AC6: 2739616 | AD6: 2739616 | AE6: 2739616 | AF6: 2739616 | AG6: 2739616 | AH6: 2739616 | AI6: 2739616 | AJ6: 2739616 | AK6: 2739616 | AL6: 2739616 | AM6: 2739616 | AN6: 2739616 | AO6: 2739616 | AP6: 2739616 | AQ6: 2739616 | AR6: 2739616 | AS6: 2739616 | AT6: 2739616 | AU6: 2739616 | AV6: 2739616 | AW6: 2739616 | AX6: 2739616 | AY6: 2739616 | AZ6: 2739616 | BA6: 2739616 | BB6: 2739616 | BC6: 2739616 | BD6: 2739616 | BE6: 2739616 | BF6: 2739616 | BG6: 2739616 | BH6: 2739616 | BI6: 2739616
A7: RETIROS EMPRESAS | B7: 3440000 | C7: 3440000 | D7: 3440000 | E7: 3440000 | F7: 3440000 | G7: 3440000 | H7: 3440000 | I7: 3440000 | J7: 3440000 | K7: 3440000 | L7: 3440000 | M7: 3440000 | N7: 3440000 | O7: 3440000 | P7: 3440000 | Q7: 3440000 | R7: 3440000 | S7: 3440000 | T7: 3440000 | U7: 3440000 | V7: 3440000 | W7: 3440000 | X7: 3440000 | Y7: 3440000 | Z7: 3440000 | AA7: 3440000 | AB7: 3440000 | AC7: 3440000 | AD7: 3440000 | AE7: 3440000 | AF7: 3440000 | AG7: 3440000 | AH7: 3440000 | AI7: 3440000 | AJ7: 3440000 | AK7: 3440000 | AL7: 3440000 | AM7: 3440000 | AN7: 3440000 | AO7: 3440000 | AP7: 3440000 | AQ7: 3440000 | AR7: 3440000 | AS7: 3440000 | AT7: 3440000 | AU7: 3440000 | AV7: 3440000 | AW7: 3440000 | AX7: 3440000 | AY7: 3440000 | AZ7: 3440000 | BA7: 3440000 | BB7: 3440000 | BC7: 3440000 | BD7: 3440000 | BE7: 3440000 | BF7: 3440000 | BG7: 3440000 | BH7: 3440000 | BI7: 3440000
A8: ARRIENDOS MK 9 | B8: 1800000 | C8: 1800000 | D8: 1800000 | E8: 1800000 | F8: 1800000 | G8: 1800000 | H8: 1800000 | I8: 1800000 | J8: 1800000 | K8: 1800000 | L8: 1800000 | M8: 1800000 | N8: 1800000 | O8: 1800000 | P8: 1800000 | Q8: 1800000 | R8: 1800000 | S8: 1800000 | T8: 1800000 | U8: 1800000 | V8: 1800000 | W8: 1800000 | X8: 1800000 | Y8: 1800000 | Z8: 1800000 | AA8: 1800000 | AB8: 1800000 | AC8: 1800000 | AD8: 1800000 | AE8: 1800000 | AF8: 1800000 | AG8: 1800000 | AH8: 1800000 | AI8: 1800000 | AJ8: 1800000 | AK8: 1800000 | AL8: 1800000 | AM8: 1800000 | AN8: 1800000 | AO8: 1800000 | AP8: 1800000 | AQ8: 1800000 | AR8: 1800000 | AS8: 1800000 | AT8: 1800000 | AU8: 1800000 | AV8: 1800000 | AW8: 1800000 | AX8: 1800000 | AY8: 1800000 | AZ8: 1800000 | BA8: 1800000 | BB8: 1800000 | BC8: 1800000 | BD8: 1800000 | BE8: 1800000 | BF8: 1800000 | BG8: 1800000 | BH8: 1800000 | BI8: 1800000
A9: ARRIENDOS JJ 3 PRIETO | B9: 1000000 | C9: 1000000 | D9: 1000000 | E9: 1000000 | F9: 1000000 | G9: 1000000 | H9: 1000000 | I9: 1000000 | J9: 1000000 | K9: 1000000 | L9: 1000000 | M9: 1000000 | N9: 1000000 | O9: 1000000 | P9: 1000000 | Q9: 1000000 | R9: 1000000 | S9: 1000000 | T9: 1000000 | U9: 1000000 | V9: 1000000 | W9: 1000000 | X9: 1000000 | Y9: 1000000 | Z9: 1000000 | AA9: 1000000 | AB9: 1000000 | AC9: 1000000 | AD9: 1000000 | AE9: 1000000 | AF9: 1000000 | AG9: 1000000 | AH9: 1000000 | AI9: 1000000 | AJ9: 1000000 | AK9: 1000000 | AL9: 1000000 | AM9: 1000000 | AN9: 1000000 | AO9: 1000000 | AP9: 1000000 | AQ9: 1000000 | AR9: 1000000 | AS9: 1000000 | AT9: 1000000 | AU9: 1000000 | AV9: 1000000 | AW9: 1000000 | AX9: 1000000 | AY9: 1000000 | AZ9: 1000000 | BA9: 1000000 | BB9: 1000000 | BC9: 1000000 | BD9: 1000000 | BE9: 1000000 | BF9: 1000000 | BG9: 1000000 | BH9: 1000000 | BI9: 1000000
A10: ARRIENDO BODEGAS Y ESTACIONAMIENTOS MK 3B JJP 3E3B | B10: 230000 | C10: 230000 | D10: 230000 | E10: 230000 | F10: 230000 | G10: 230000 | H10: 230000 | I10: 230000 | J10: 230000 | K10: 230000 | L10: 230000 | M10: 230000 | N10: 230000 | O10: 230000 | P10: 230000 | Q10: 230000 | R10: 230000 | S10: 230000 | T10: 230000 | U10: 230000 | V10: 230000 | W10: 230000 | X10: 230000 | Y10: 230000 | Z10: 230000 | AA10: 230000 | AB10: 230000 | AC10: 230000 | AD10: 230000 | AE10: 230000 | AF10: 230000 | AG10: 230000 | AH10: 230000 | AI10: 230000 | AJ10: 230000 | AK10: 230000 | AL10: 230000 | AM10: 230000 | AN10: 230000 | AO10: 230000 | AP10: 230000 | AQ10: 230000 | AR10: 230000 | AS10: 230000 | AT10: 230000 | AU10: 230000 | AV10: 230000 | AW10: 230000 | AX10: 230000 | AY10: 230000 | AZ10: 230000 | BA10: 230000 | BB10: 230000 | BC10: 230000 | BD10: 230000 | BE10: 230000 | BF10: 230000 | BG10: 230000 | BH10: 230000 | BI10: 230000
A11: FIDEL OTEIZA 1841 DEPARTAMENTO 41 E | B11: 350000 | C11: 350000 | D11: 350000 | E11: 350000 | F11: 350000 | G11: 350000 | H11: 350000 | I11: 350000 | J11: 350000 | K11: 350000 | L11: 350000 | M11: 350000 | N11: 350000 | O11: 350000 | P11: 350000 | Q11: 350000 | R11: 350000 | S11: 350000 | T11: 350000 | U11: 350000 | V11: 350000 | W11: 350000 | X11: 350000 | Y11: 350000 | Z11: 350000 | AA11: 350000 | AB11: 350000 | AC11: 350000 | AD11: 350000 | AE11: 350000 | AF11: 350000 | AG11: 350000 | AH11: 350000 | AI11: 350000 | AJ11: 350000 | AK11: 350000 | AL11: 350000 | AM11: 350000 | AN11: 350000 | AO11: 350000 | AP11: 350000 | AQ11: 350000 | AR11: 350000 | AS11: 350000 | AT11: 350000 | AU11: 350000 | AV11: 350000 | AW11: 350000 | AX11: 350000 | AY11: 350000 | AZ11: 350000 | BA11: 350000 | BB11: 350000 | BC11: 350000 | BD11: 350000 | BE11: 350000 | BF11: 350000 | BG11: 350000 | BH11: 350000 | BI11: 350000
A12: ARRIENDOS OFICINA LAS CONDES ESTORIL (UF) | B12: 650000 | C12: 650000 | D12: 650000 | E12: 650000 | F12: 650000 | G12: 650000 | H12: 650000 | I12: 650000 | J12: 650000 | K12: 650000 | L12: 650000 | M12: 650000 | N12: 650000 | O12: 650000 | P12: 650000 | Q12: 650000 | R12: 650000 | S12: 650000 | T12: 650000 | U12: 650000 | V12: 650000 | W12: 650000 | X12: 650000 | Y12: 650000 | Z12: 650000 | AA12: 650000 | AB12: 650000 | AC12: 650000 | AD12: 650000 | AE12: 650000 | AF12: 650000 | AG12: 650000 | AH12: 650000 | AI12: 650000 | AJ12: 650000 | AK12: 650000 | AL12: 650000 | AM12: 650000 | AN12: 650000 | AO12: 650000 | AP12: 650000 | AQ12: 650000 | AR12: 650000 | AS12: 650000 | AT12: 650000 | AU12: 650000 | AV12: 650000 | AW12: 650000 | AX12: 650000 | AY12: 650000 | AZ12: 650000 | BA12: 650000 | BB12: 650000 | BC12: 650000 | BD12: 650000 | BE12: 650000 | BF12: 650000 | BG12: 650000 | BH12: 650000 | BI12: 579000
A13: ARRIENDOS CONSTANTINO 6 | B13: =6*210000 -> 1260000 | C13: =6*210000 -> 1260000 | D13: =6*210000 -> 1260000 | E13: =6*210000 -> 1260000 | F13: =6*210000 -> 1260000 | G13: =6*210000 -> 1260000 | H13: =6*210000 -> 1260000 | I13: =6*210000 -> 1260000 | ... Z13: =6*210000 -> 1260000 | AA13: 972350 | AB13: 972350 | AC13: 972350 | AD13: 972350 | AE13: 972350 | AF13: 972350 | AG13: 972350 | AH13: 972350 | AI13: 972350 | AJ13: 972350 | AK13: 972350 | AL13: 972350 | AM13: 972350 | AN13: 972350 | AO13: 972350 | AP13: 972350 | AQ13: 972350 | AR13: 972350 | AS13: 972350 | AT13: 972350 | AU13: 972350 | AV13: 972350 | AW13: 972350 | AX13: 972350 | AY13: 972350 | AZ13: 972350 | BA13: 972350 | BB13: 972350 | BC13: 972350 | BD13: 972350 | BE13: 972350 | BF13: 972350 | BG13: 972350 | BH13: 972350 | BI13: 972350
A14: ADMINISTRADORA BBRR | B14: 520000 | C14: 520000 | D14: 520000 | E14: 520000 | F14: 520000 | G14: 520000 | H14: 520000 | I14: 520000 | J14: 520000 | K14: 520000 | L14: 520000 | M14: 520000 | N14: 520000 | O14: 520000 | P14: 520000 | Q14: 520000 | R14: 520000 | S14: 520000 | T14: 520000
A15: SUELDO PAULA | B15: =2000000/(1-0.1575) -> 2373887.2 | C15: =2000000/(1-0.1575) -> 2373887.2 | D15: =2000000/(1-0.1575) -> 2373887.2 | E15: =2000000/(1-0.1575) -> 2373887.2 | F15: =2000000/(1-0.1575) -> 2373887.2 | G15: =2000000/(1-0.1575) -> 2373887.2 | H15: =2000000/(1-0.1575) -> 2373887.2 | I15: =2000000/(1-0.1575) -> 2373887.2 | ... BI15: =2000000/(1-0.1575) -> 2373887.2
A16: CLASES UNIVERSIDADES | B16: 0 | C16: 1624190.1 | D16: =1000000/(1.1575) -> 863930.89 | E16: =C16 -> 1624190.1 | F16: 1500000 | G16: 0 | H16: 0 | I16: 0 | J16: 0 | K16: 0 | L16: 0 | M16: 0 | N16: 0 | O16: 0 | P16: 0 | R16: 0 | S16: 0 | T16: 0 | U16: 0 | V16: 0 | W16: 0 | X16: 0 | Y16: 0 | Z16: 0 | AA16: 0 | AB16: 0 | AC16: 3689000 | AD16: 0 | AE16: 0 | AF16: 0 | AG16: 0 | AH16: 0 | AI16: 0 | AJ16: 0 | AK16: 0 | AL16: 0 | AM16: 0 | AN16: 0 | AO16: 3689000 | AP16: 0 | AQ16: 0 | AR16: 0 | AS16: 0 | AT16: 0 | AU16: 0 | AV16: 0 | AW16: 0 | AX16: 0 | AY16: 0 | AZ16: 0 | BA16: 3689000 | BB16: 0 | BC16: 0 | BD16: 0 | BE16: 0 | BF16: 0 | BG16: 0 | BH16: 0 | BI16: 0
A17: PAGOS MEME ARRIENDO A BANCO ITAU RODRIGO FUENZALIDA (UF) | B17: 4900000 | C17: 4900000 | D17: 4900000 | E17: 4900000 | F17: 4900000 | G17: 4900000 | H17: 4900000 | I17: 4900000 | J17: 4900000 | K17: 4900000 | L17: 4900000 | M17: 4900000 | N17: 4900000 | O17: 4900000 | P17: 4900000 | Q17: 4900000 | R17: 4900000 | S17: 4900000 | T17: 4900000 | U17: 4900000 | V17: 4900000 | W17: 4900000 | X17: 4900000 | Y17: 4900000 | Z17: 4900000 | AA17: 4900000 | AB17: 4900000 | AC17: 4900000 | AD17: 4900000 | AE17: 4900000 | AF17: 4900000 | AG17: 4900000 | AH17: 4900000 | AI17: 4900000 | AJ17: 4900000 | AK17: 4900000 | AL17: 4900000 | AM17: 4900000 | AN17: 4900000 | AO17: 4900000 | AP17: 4900000 | AQ17: 4900000 | AR17: 4900000 | AS17: 4900000 | AT17: 4900000 | AU17: 4900000 | AV17: 4900000 | AW17: 4900000 | AX17: 4900000 | AY17: 4900000 | AZ17: 4900000 | BA17: 4900000 | BB17: 4900000 | BC17: 4900000 | BD17: 4900000 | BE17: 4900000 | BF17: 4900000 | BG17: 4900000 | BH17: 4900000 | BI17: 4900000
A18: INTERESES INVERSIONES FINANCIERAS (**conectar a dividendos de renta variable resultante) | B18: =3986184+552083 -> 4538267 | C18: =3986184+552083 -> 4538267 | D18: =3986184+552083 -> 4538267 | E18: =3986184+552083 -> 4538267 | F18: =3986184+552083 -> 4538267 | G18: =3986184+552083 -> 4538267 | H18: =3986184+552083 -> 4538267 | I18: =3986184+552083 -> 4538267 | ... BI18: =3986184+552083 -> 4538267
A19: ARRIENDOS PROPIEDADES CON GERMAN PERSONAL WARRENSMID 15 Y LOCALES (UF) | B19: 1614000 | C19: 1614000 | D19: 1614000 | E19: 1614000 | F19: 1614000 | G19: 1614000 | H19: 1614000 | I19: 1614000 | J19: 1614000 | K19: 1614000 | L19: 1614000 | M19: 1614000 | N19: 1614000 | O19: 1614000 | P19: 1614000 | Q19: 1614000 | R19: 1614000 | S19: 1614000 | T19: 1614000 | U19: 1614000 | V19: 1614000 | W19: 1614000 | X19: 1614000 | Y19: 1614000 | Z19: 1614000 | AA19: 1614000 | AB19: 1614000 | AC19: 1614000 | AD19: 1614000 | AE19: 1614000 | AF19: 1614000 | AG19: 1614000 | AH19: 1614000 | AI19: 1614000 | AJ19: 1614000 | AK19: 1614000 | AL19: 1614000 | AM19: 1614000 | AN19: 1614000 | AO19: 1614000 | AP19: 1614000 | AQ19: 1614000 | AR19: 1614000 | AS19: 1614000 | AT19: 1614000 | AU19: 1614000 | AV19: 1614000 | AW19: 1614000 | AX19: 1614000 | AY19: 1614000 | AZ19: 1614000 | BA19: 1614000 | BB19: 1614000 | BC19: 1614000 | BD19: 1614000 | BE19: 1614000 | BF19: 1614000 | BG19: 1614000 | BH19: 1614000 | BI19: 1614000
A20: ARRIENDOS PROPIEDADES CON GERMAN POR PRAGA | B20: 3574385 | C20: 3574385 | D20: 3574385 | E20: 3574385 | F20: 3574385 | G20: 3574385 | H20: 3574385 | I20: 3574385 | J20: 3574385 | K20: 3574385 | L20: 3574385 | M20: 3574385 | N20: 3574385 | O20: 3574385 | P20: 3574385 | Q20: 3574385 | R20: 3574385 | S20: 3574385 | T20: 3574385 | U20: 3574385 | V20: 3574385 | W20: 3574385 | X20: 3574385 | Y20: 3574385 | Z20: 3574385 | AA20: 3574385 | AB20: 3574385 | AC20: 3574385 | AD20: 3574385 | AE20: 3574385 | AF20: 3574385 | AG20: 3574385 | AH20: 3574385 | AI20: 3574385 | AJ20: 3574385 | AK20: 3574385 | AL20: 3574385 | AM20: 3574385 | AN20: 3574385 | AO20: 3574385 | AP20: 3574385 | AQ20: 3574385 | AR20: 3574385 | AS20: 3574385 | AT20: 3574385 | AU20: 3574385 | AV20: 3574385 | AW20: 3574385 | AX20: 3574385 | AY20: 3574385 | AZ20: 3574385 | BA20: 3574385 | BB20: 3574385 | BC20: 3574385 | BD20: 3574385 | BE20: 3574385 | BF20: 3574385 | BG20: 3574385 | BH20: 3574385 | BI20: 3574385
A21: PAGO VALLE CENTRO A NV (UF 31,25) ** 110 cuotas | B21: =31.25*40850 -> 1276562.5 | C21: 1233967 | D21: 1233967 | E21: 1233967 | F21: 1233967 | G21: 1233967 | H21: 1233967 | I21: 1233967 | J21: 1233967 | K21: 1233967 | L21: 1233967 | M21: 1233967 | N21: 1233967 | O21: 1233967 | P21: 1233967 | Q21: 1233967 | R21: 1233967 | S21: 1233967 | T21: 1233967 | U21: 1233967 | V21: 1233967 | W21: 1233967 | X21: 1233967 | Y21: 1233967 | Z21: 1233967 | AA21: 1233967 | AB21: 1233967 | AC21: 1233967 | AD21: 1233967 | AE21: 1233967 | AF21: 1233967 | AG21: 1233967 | AH21: 1233967 | AI21: 1233967 | AJ21: 1233967 | AK21: 1233967 | AL21: 1233967 | AM21: 1233967 | AN21: 1233967 | AO21: 1233967 | AP21: 1233967 | AQ21: 1233967 | AR21: 1233967 | AS21: 1233967 | AT21: 1233967 | AU21: 1233967 | AV21: 1233967 | AW21: 1233967 | AX21: 1233967 | AY21: 1233967 | AZ21: 1233967 | BA21: 1233967 | BB21: 1233967 | BC21: 1233967 | BD21: 1233967 | BE21: 1233967 | BF21: 1233967 | BG21: 1233967 | BH21: 1233967 | BI21: 1233967
A22: PAGOS CAPITAL OFFICE | B22: 0 | C22: 0 | D22: 0 | E22: 26000000 | F22: 0 | G22: 0 | H22: 0 | I22: 16800000 | J22: 0 | K22: 0 | L22: 0 | M22: 0 | N22: 0 | O22: 0 | P22: 0 | Q22: 26000000 | R22: 0 | S22: 0 | T22: 0 | U22: 16800000 | V22: 0 | W22: 0 | X22: 0 | Y22: 0 | Z22: 0 | AA22: 0 | AB22: 0 | AC22: 26000000 | AD22: 0 | AE22: 0 | AF22: 0 | AG22: 16800000 | AH22: 0 | AI22: 0 | AJ22: 0 | AK22: 0 | AL22: 0 | AM22: 0 | AN22: 0 | AO22: 26000000 | AP22: 0 | AQ22: 0 | AR22: 0 | AS22: 16800000 | AT22: 0 | AU22: 0 | AV22: 0 | AW22: 0 | AX22: 0 | AY22: 0 | AZ22: 0 | BA22: 26000000 | BB22: 0 | BC22: 0 | BD22: 0 | BE22: 16800000 | BF22: 0 | BG22: 0 | BH22: 0 | BI22: 0
A23: OTROS INGRESOS | B23: 0 | C23: 0 | D23: 0 | E23: 0 | F23: 0 | G23: 0 | H23: 0 | I23: 0 | J23: 0 | K23: 0 | L23: 0 | M23: 0 | N23: 0 | O23: 0 | P23: 0 | Q23: 0 | R23: 0 | S23: 0 | T23: 0 | U23: 0 | V23: 0 | W23: 0 | X23: 0 | Y23: 0 | Z23: 0 | AA23: 0 | AB23: 0 | AC23: 0 | AD23: 0 | AE23: 0 | AF23: 0 | AG23: 0 | AH23: 0 | AI23: 0 | AJ23: 0 | AK23: 0 | AL23: 0 | AM23: 0 | AN23: 0 | AO23: 0 | AP23: 0 | AQ23: 0 | AR23: 0 | AS23: 0 | AT23: 0 | AU23: 0 | AV23: 0 | AW23: 0 | AX23: 0 | AY23: 0 | AZ23: 0 | BA23: 0 | BB23: 0 | BC23: 0 | BD23: 0 | BE23: 0 | BF23: 0 | BG23: 0 | BH23: 0 | BI23: 0
A24: ARRIENDOS BOULEBARD | B24: 8806064 | C24: 8806064 | D24: 8806064 | E24: 8806064 | F24: 8806064 | G24: 8806064 | H24: 8806064 | I24: 8806064 | J24: 8806064 | K24: 8806064 | L24: 8806064 | M24: 8806064 | N24: 8806064 | O24: 8806064 | P24: 8806064 | Q24: 8806064 | R24: 8806064 | S24: 8806064 | T24: 8806064 | U24: 8806064 | V24: 8806064 | W24: 8806064 | X24: 8806064 | Y24: 8806064 | Z24: 8806064 | AA24: 8806064 | AB24: 8806064 | AC24: 8806064 | AD24: 8806064 | AE24: 8806064 | AF24: 8806064 | AG24: 8806064 | AH24: 8806064 | AI24: 8806064 | AJ24: 8806064 | AK24: 8806064 | AL24: 8806064 | AM24: 8806064 | AN24: 8806064 | AO24: 8806064 | AP24: 8806064 | AQ24: 8806064 | AR24: 8806064 | AS24: 8806064 | AT24: 8806064 | AU24: 8806064 | AV24: 8806064 | AW24: 8806064 | AX24: 8806064 | AY24: 8806064 | AZ24: 8806064 | BA24: 8806064 | BB24: 8806064 | BC24: 8806064 | BD24: 8806064 | BE24: 8806064 | BF24: 8806064 | BG24: 8806064 | BH24: 8806064 | BI24: 8806064
A25: Efecto Inflacion | B25: 4389035 | C25: 4389035 | D25: 4389035 | E25: 4389035 | F25: 4389035 | G25: 4389035 | H25: 4389035 | I25: 4389035 | J25: 4389035 | K25: 4389035 | L25: 4389035 | M25: 4389035 | N25: 4389035 | O25: 4389035 | P25: 4389035 | Q25: 4389035 | R25: 4389035 | S25: 4389035 | T25: 4389035 | U25: 4389035 | V25: 4389035 | W25: 4389035 | X25: 4389035 | Y25: 4389035 | Z25: 4389035 | AA25: 4389035 | AB25: 4389035 | AC25: 4389035 | AD25: 4389035 | AE25: 4389035 | AF25: 4389035 | AG25: 4389035 | AH25: 4389035 | AI25: 4389035 | AJ25: 4389035 | AK25: 4389035 | AL25: 4389035 | AM25: 4389035 | AN25: 4389035 | AO25: 4389035 | AP25: 4389035 | AQ25: 4817967 | AR25: 4389035 | AS25: 4389035 | AT25: 4389035 | AU25: 4389035 | AV25: 4389035 | AW25: 4389035 | AX25: 4389035 | AY25: 4389035 | AZ25: 4389035 | BA25: 4389035 | BB25: 4389035 | BC25: 4389035 | BD25: 4389035 | BE25: 4389035 | BF25: 4389035 | BG25: 4389035 | BH25: 4389035 | BI25: 4389035
A26: TOTAL INGRESOS | B26: =SUM(B6:B25) -> 43357201 | C26: =SUM(C6:C25) -> 45043411 | D26: =SUM(D6:D25) -> 44283152 | E26: =SUM(E6:E25) -> 71043411 | F26: =SUM(F6:F25) -> 44919221 | G26: =SUM(G6:G25) -> 43419221 | H26: =SUM(H6:H25) -> 43419221 | I26: =SUM(I6:I25) -> 60219221 | ... BI26: =SUM(BI6:BI25) -> 42540571
A28: EGRESOS
A29: PAGO DIVIDENDO CASA SANTUARIO SANTANDER (UF) | B29: 9950000 | C29: 9950000 | D29: 9950000 | E29: 9950000 | F29: 9950000 | G29: 9950000 | H29: 9950000 | I29: 9950000 | J29: 9950000 | K29: 9950000 | L29: 9950000 | M29: 9950000 | N29: 9950000 | O29: 9950000 | P29: 9950000 | Q29: 9950000 | R29: 9950000 | S29: 9950000 | T29: 9950000 | U29: 9950000 | V29: 9950000 | W29: 9950000 | X29: 9950000 | Y29: 9950000 | Z29: 9950000 | AA29: 9950000 | AB29: 9950000 | AC29: 9950000 | AD29: 9950000 | AE29: 9950000 | AF29: 9950000 | AG29: 9950000 | AH29: 9950000 | AI29: 9950000 | AJ29: 9950000 | AK29: 9950000 | AL29: 9950000 | AM29: 9950000 | AN29: 9950000 | AO29: 9950000 | AP29: 9950000 | AQ29: 9950000 | AR29: 0 | AS29: 0 | AT29: 0 | AU29: 0 | AV29: 0 | AW29: 0 | AX29: 0 | AY29: 0 | AZ29: 0 | BA29: 0 | BB29: 0 | BC29: 0 | BD29: 0 | BE29: 0 | BF29: 0 | BG29: 0 | BH29: 0 | BI29: 0
A30: CASA NUBA** | B30: 0 | C30: 0 | D30: 0 | E30: 0 | F30: 0 | G30: 0 | H30: 0 | I30: 0 | J30: 0 | K30: 0 | L30: 0 | M30: 0 | N30: 0 | O30: 0 | P30: 0 | Q30: 0 | R30: 0 | S30: 0 | T30: 0 | U30: 0 | V30: 0 | W30: 0 | X30: 0 | Y30: 0 | Z30: 0 | AA30: 0 | AB30: 0 | AC30: 0 | AD30: 0 | AE30: 0 | AF30: 0 | AG30: 0 | AH30: 0 | AI30: 0 | AJ30: 0 | AK30: 0 | AL30: 0 | AM30: 0 | AN30: 0 | AO30: 0 | AP30: 0 | AQ30: 0 | AR30: 0 | AS30: 0 | AT30: 0 | AU30: 0 | AV30: 0 | AW30: 0 | AX30: 0 | AY30: 0 | AZ30: 0 | BA30: 0 | BB30: 0 | BC30: 0 | BD30: 0 | BE30: 0 | BF30: 0 | BG30: 0 | BH30: 0 | BI30: 0
A31: ADMINISTRACION PROPIEDADES | B31: 280000 | C31: 280000 | D31: 280000 | E31: 280000 | F31: 280000 | G31: 280000 | H31: 280000 | I31: 280000 | J31: 280000 | K31: 280000 | L31: 280000 | M31: 280000 | N31: 280000 | O31: 280000 | P31: 280000 | Q31: 280000 | R31: 280000 | S31: 280000 | T31: 280000 | U31: 280000 | V31: 280000 | W31: 280000 | X31: 280000 | Y31: 280000 | Z31: 280000 | AA31: 280000 | AB31: 280000 | AC31: 280000 | AD31: 280000 | AE31: 280000 | AF31: 280000 | AG31: 280000 | AH31: 280000 | AI31: 280000 | AJ31: 280000 | AK31: 280000 | AL31: 280000 | AM31: 280000 | AN31: 280000 | AO31: 280000 | AP31: 280000 | AQ31: 280000 | AR31: 280000 | AS31: 280000 | AT31: 280000 | AU31: 280000 | AV31: 280000 | AW31: 280000 | AX31: 280000 | AY31: 280000 | AZ31: 280000 | BA31: 280000 | BB31: 280000 | BC31: 280000 | BD31: 280000 | BE31: 280000 | BF31: 280000 | BG31: 280000 | BH31: 280000 | BI31: 280000
A32: AGUA | B32: 31603 | C32: 31603 | D32: 31603 | E32: 31603 | F32: 39000 | G32: 39000 | H32: 39000 | I32: 39000 | J32: 39000 | K32: 39000 | L32: 39000 | M32: 39000 | N32: 39000 | O32: 39000 | P32: 39000 | Q32: 39000 | R32: 39000 | S32: 39000 | T32: 39000 | U32: 39000 | V32: 39000 | W32: 39000 | X32: 39000 | Y32: 39000 | Z32: 39000 | AA32: 39000 | AB32: 39000 | AC32: 39000 | AD32: 39000 | AE32: 100000 | AF32: 100000 | AG32: 100000 | AH32: 100000 | AI32: 100000 | AJ32: 100000 | AK32: 100000 | AL32: 100000 | AM32: 100000 | AN32: 100000 | AO32: 100000 | AP32: 100000 | AQ32: 100000 | AR32: 100000 | AS32: 100000 | AT32: 100000 | AU32: 100000 | AV32: 100000 | AW32: 100000 | AX32: 100000 | AY32: 100000 | AZ32: 100000 | BA32: 100000 | BB32: 100000 | BC32: 100000 | BD32: 100000 | BE32: 100000 | BF32: 100000 | BG32: 100000 | BH32: 100000 | BI32: 100000
A33: NANAS | B33: 685800 | C33: 685800 | D33: 685800 | E33: 685800 | F33: 685800 | G33: 685800 | H33: 685800 | I33: 685800 | J33: 685800 | K33: 685800 | L33: 685800 | M33: 685800 | N33: 685800 | O33: 685800 | P33: 685800 | Q33: 685800 | R33: 685800 | S33: 685800 | T33: 685800 | U33: 685800 | V33: 685800 | W33: 685800 | X33: 685800 | Y33: 685800 | Z33: 685800 | AA33: 685800 | AB33: 685800 | AC33: 685800 | AD33: 685800 | AE33: 685800 | AF33: 685800 | AG33: 685800 | AH33: 685800 | AI33: 685800 | AJ33: 685800 | AK33: 685800 | AL33: 685800 | AM33: 685800 | AN33: 685800 | AO33: 685800 | AP33: 685800 | AQ33: 685800 | AR33: 685800 | AS33: 685800 | AT33: 685800 | AU33: 685800 | AV33: 685800 | AW33: 685800 | AX33: 685800 | AY33: 685800 | AZ33: 685800 | BA33: 685800 | BB33: 685800 | BC33: 685800 | BD33: 685800 | BE33: 685800 | BF33: 685800 | BG33: 685800 | BH33: 685800 | BI33: 685800
A34: ARREGLOS SANTUARIO PARA VENTA | B34: 0 | C34: 0 | D34: 0 | E34: 0 | F34: 0 | G34: 0 | H34: 0 | I34: 0 | J34: 0 | K34: 0 | L34: 0 | M34: 0 | N34: 0 | O34: 0 | P34: 0 | Q34: 0 | R34: 0 | S34: 0 | T34: 5000000 | U34: 5000000 | V34: 5000000 | W34: 5000000 | X34: 0 | Y34: 0 | Z34: 0 | AA34: 0 | AB34: 0 | AC34: 0 | AD34: 0 | AE34: 0 | AF34: 0 | AG34: 0 | AH34: 0 | AI34: 0 | AJ34: 0 | AK34: 0 | AL34: 0 | AM34: 0 | AN34: 0 | AO34: 0 | AP34: 0 | AQ34: 0 | AR34: 0 | AS34: 0 | AT34: 0 | AU34: 0 | AV34: 0 | AW34: 0 | AX34: 0 | AY34: 0 | AZ34: 0 | BA34: 0 | BB34: 0 | BC34: 0 | BD34: 0 | BE34: 0 | BF34: 0 | BG34: 0 | BH34: 0 | BI34: 0
A35: ARRIENDO DOS ESTACIONAMIENTOS LA LUMA | B35: 60000 | C35: 60000 | D35: 60000 | E35: 60000 | F35: 60000 | G35: 60000 | H35: 60000 | I35: 60000 | J35: 60000 | K35: 60000 | L35: 60000 | M35: 60000 | N35: 60000 | O35: 60000 | P35: 60000 | Q35: 60000 | R35: 60000 | S35: 60000 | T35: 60000 | U35: 60000 | V35: 60000 | W35: 60000 | X35: 60000 | Y35: 0 | Z35: 0 | AA35: 0 | AB35: 0 | AC35: 0 | AD35: 0 | AE35: 0 | AF35: 0 | AG35: 0 | AH35: 0 | AI35: 0 | AJ35: 0 | AK35: 150000 | AL35: 0 | AM35: 0 | AN35: 0 | AO35: 0 | AP35: 0 | AQ35: 0 | AR35: 0 | AS35: 0 | AT35: 0 | AU35: 0 | AV35: 0 | AW35: 0 | AX35: 0 | AY35: 0 | AZ35: 0 | BA35: 0 | BB35: 0 | BC35: 0 | BD35: 0 | BE35: 0 | BF35: 0 | BG35: 0 | BH35: 0 | BI35: 0
A36: ARRIENDO LA LUMA | B36: 3500000 | C36: 3500000 | D36: 3500000 | E36: 3500000 | F36: 3500000 | G36: 3500000 | H36: 3500000 | I36: 3500000 | J36: 3500000 | K36: 3500000 | L36: 3500000 | M36: 3500000 | N36: 3500000 | O36: 3500000 | P36: 3500000 | Q36: 3500000 | R36: 3500000 | S36: 3500000 | T36: 3500000 | U36: 3500000 | V36: 3500000 | W36: 3500000 | X36: 3500000 | Y36: 3500000 | Z36: 3500000 | AA36: 3500000 | AB36: 3500000 | AC36: 3500000 | AD36: 0 | AE36: 0 | AF36: 0 | AG36: 0 | AH36: 0 | AI36: 0 | AJ36: 0 | AK36: 0 | AL36: 0 | AM36: 0 | AN36: 0 | AO36: 0 | AP36: 0 | AQ36: 0 | AR36: 0 | AS36: 0 | AT36: 0 | AU36: 0 | AV36: 0 | AW36: 0 | AX36: 0 | AY36: 0 | AZ36: 0 | BA36: 0 | BB36: 0 | BC36: 0 | BD36: 0 | BE36: 0 | BF36: 0 | BG36: 0 | BH36: 0 | BI36: 0
A37: DEDUCIBLE SEGUROS AUTOS | B37: 0 | C37: 0 | D37: 0 | E37: 0 | F37: 0 | G37: 0 | H37: 0 | I37: 0 | K37: 0 | L37: 0 | M37: 0 | N37: 0 | O37: 0 | P37: 0 | Q37: 0 | R37: 0 | S37: 0 | T37: 0 | U37: 0 | V37: 0 | W37: 0 | X37: 0 | Y37: 0 | Z37: 0 | AB37: 0 | AC37: 0 | AD37: 0 | AE37: 0 | AF37: 0 | AG37: 0 | AH37: 0 | AI37: 0 | AJ37: 0 | AK37: 0 | AL37: 0 | AM37: 0 | AN37: 0 | AO37: 0 | AP37: 0 | AQ37: 0 | AS37: 0 | AT37: 0 | AU37: 0 | AV37: 0 | AW37: 0 | AX37: 0 | AY37: 0 | AZ37: 0 | BA37: 0 | BB37: 0 | BC37: 0 | BD37: 0 | BE37: 0 | BF37: 0 | BG37: 0 | BH37: 0
A38: AUTOS BENCINA | B38: 350000 | C38: 350000 | D38: 350000 | E38: 350000 | F38: 350000 | G38: 350000 | H38: 350000 | I38: 350000 | J38: 350000 | K38: 350000 | L38: 350000 | M38: 350000 | N38: 350000 | O38: 350000 | P38: 350000 | Q38: 350000 | R38: 350000 | S38: 350000 | T38: 350000 | U38: 350000 | V38: 350000 | W38: 350000 | X38: 350000 | Y38: 350000 | Z38: 350000 | AA38: 350000 | AB38: 350000 | AC38: 350000 | AD38: 350000 | AE38: 350000 | AF38: 350000 | AG38: 350000 | AH38: 350000 | AI38: 350000 | AJ38: 350000 | AK38: 350000 | AL38: 350000 | AM38: 350000 | AN38: 350000 | AO38: 350000 | AP38: 350000 | AQ38: 350000 | AR38: 350000 | AS38: 350000 | AT38: 350000 | AU38: 350000 | AV38: 350000 | AW38: 350000 | AX38: 350000 | AY38: 350000 | AZ38: 350000 | BA38: 350000 | BB38: 350000 | BC38: 350000 | BD38: 350000 | BE38: 350000 | BF38: 350000 | BG38: 350000 | BH38: 350000 | BI38: 350000
A39: BODEGA PASEO TAMARUGO | B39: 345902 | C39: 345902 | D39: 345902 | E39: 345902 | F39: 345902 | G39: 345902 | H39: 345902 | I39: 345902 | J39: 345902 | K39: 345902 | L39: 345902 | M39: 345902 | N39: 345902 | O39: 345902 | P39: 345902 | Q39: 345902 | R39: 345902 | S39: 345902 | T39: 345902 | U39: 345902 | V39: 345902 | W39: 345902 | X39: 345902 | Y39: 345902 | Z39: 345902 | AA39: 345902 | AB39: 345902 | AC39: 345902 | AD39: 345902 | AE39: 345902 | AF39: 345902 | AG39: 345902 | AH39: 345902 | AI39: 345902 | AJ39: 345902 | AK39: 345902 | AL39: 345902 | AM39: 345902 | AN39: 345902 | AO39: 345902 | AP39: 345902 | AQ39: 345902 | AR39: 345902 | AS39: 345902 | AT39: 345902 | AU39: 345902 | AV39: 0 | AW39: 0 | AX39: 0 | AY39: 0 | AZ39: 0 | BA39: 0 | BB39: 0 | BC39: 0 | BD39: 0 | BE39: 0 | BF39: 0 | BG39: 0 | BH39: 0 | BI39: 0
A40: CAROLA | B40: 1250000 | C40: 1250000 | D40: 1250000 | E40: 1250000 | F40: 1250000 | G40: 1250000 | H40: 1250000 | I40: 1250000 | J40: 1250000 | K40: 1250000 | L40: 1250000 | M40: 1250000 | N40: 1250000 | O40: 1250000 | P40: 1250000 | Q40: 1250000 | R40: 1250000 | S40: 1250000 | T40: 1250000 | U40: 1250000 | V40: 1250000 | W40: 1250000 | X40: 1250000 | Y40: 1250000 | Z40: 1250000 | AA40: 1250000 | AB40: 1250000 | AC40: 1250000 | AD40: 1250000 | AE40: 1250000 | AF40: 1250000 | AG40: 1250000 | AH40: 1250000 | AI40: 1250000 | AJ40: 1250000 | AK40: 1250000 | AL40: 1250000 | AM40: 1250000 | AN40: 1250000 | AO40: 1250000 | AP40: 1250000 | AQ40: 1250000 | AR40: 1250000 | AS40: 1250000 | AT40: 1250000 | AU40: 1250000 | AV40: 1250000 | AW40: 1250000 | AX40: 1250000 | AY40: 1250000 | AZ40: 1250000 | BA40: 1250000 | BB40: 1250000 | BC40: 1250000 | BD40: 1250000 | BE40: 1250000 | BF40: 1250000 | BG40: 1250000 | BH40: 1250000 | BI40: 1250000
A41: CELULARES | B41: 0 | C41: 0 | D41: 0 | E41: 0 | F41: 0 | G41: 0 | H41: 0 | I41: 0 | J41: 0 | K41: 0 | L41: 0 | M41: 0 | N41: 0 | O41: 0 | P41: 0 | Q41: 0 | R41: 0 | S41: 0 | T41: 70000 | U41: 70000 | V41: 70000 | W41: 70000 | X41: 70000 | Y41: 70000 | Z41: 70000 | AA41: 70000 | AB41: 70000 | AC41: 70000 | AD41: 70000 | AE41: 70000 | AF41: 70000 | AG41: 70000 | AH41: 70000 | AI41: 70000 | AJ41: 70000 | AK41: 70000 | AL41: 70000 | AM41: 70000 | AN41: 70000 | AO41: 70000 | AP41: 70000 | AQ41: 70000 | AR41: 70000 | AS41: 70000 | AT41: 70000 | AU41: 70000 | AV41: 70000 | AW41: 70000 | AX41: 70000 | AY41: 70000 | AZ41: 70000 | BA41: 70000 | BB41: 70000 | BC41: 70000 | BD41: 70000 | BE41: 70000 | BF41: 70000 | BG41: 70000 | BH41: 70000 | BI41: 70000
A42: PREPARACION CLASES CRISTIAN | B42: 0 | C42: 0 | D42: 0 | E42: 0 | F42: 0 | G42: 0 | H42: 0 | I42: 0 | J42: 0 | K42: 0 | L42: 0 | M42: 0 | N42: 0 | O42: 0 | P42: 0 | Q42: 0 | R42: 0 | S42: 0 | T42: 0 | U42: 0 | V42: 0 | W42: 0 | X42: 0 | Y42: 0 | Z42: 0 | AA42: 0 | AB42: 0 | AC42: 0 | AD42: 0 | AE42: 0 | AF42: 0 | AG42: 0 | AH42: 0 | AI42: 0 | AJ42: 0 | AK42: 0 | AL42: 0 | AM42: 0 | AN42: 0 | AO42: 0 | AP42: 0 | AQ42: 0 | AR42: 0 | AS42: 0 | AT42: 0 | AU42: 0 | AV42: 0 | AW42: 0 | AX42: 0 | AY42: 0 | AZ42: 0 | BA42: 0 | BB42: 0 | BC42: 0 | BD42: 0 | BE42: 0 | BF42: 0 | BG42: 0 | BH42: 0 | BI42: 0
A43: COMIDA | B43: 3000000 | C43: 3000000 | D43: 3000000 | E43: 3000000 | F43: 3000000 | G43: 3000000 | H43: 3000000 | I43: 3000000 | J43: 3000000 | K43: 3000000 | L43: 3000000 | M43: 3000000 | N43: 3000000 | O43: 3000000 | P43: 3000000 | Q43: 3000000 | R43: 3000000 | S43: 3000000 | T43: 3000000 | U43: 3000000 | V43: 3000000 | W43: 3000000 | X43: 3000000 | Y43: 3000000 | Z43: 3000000 | AA43: 3000000 | AB43: 3000000 | AC43: 3000000 | AD43: 3000000 | AE43: 3000000 | AF43: 3000000 | AG43: 3000000 | AH43: 3000000 | AI43: 2800000 | AJ43: 2800000 | AK43: 2800000 | AL43: 2800000 | AM43: 2800000 | AN43: 2800000 | AO43: 2800000 | AP43: 2800000 | AQ43: 2800000 | AR43: 2800000 | AS43: 2800000 | AT43: 2800000 | AU43: 2800000 | AV43: 2800000 | AW43: 2800000 | AX43: 2800000 | AY43: 2800000 | AZ43: 2800000 | BA43: 2800000 | BB43: 2800000 | BC43: 2800000 | BD43: 2800000 | BE43: 2600000 | BF43: 2600000 | BG43: 2600000 | BH43: 2600000 | BI43: 2600000
A44: COMPRA CASA O DEPARTAMENTO :) | B44: 0 | C44: 0 | D44: 0 | E44: 0 | F44: 0 | G44: 0 | H44: 0 | I44: 0 | J44: 0 | K44: 0 | L44: 0 | M44: 0 | N44: 0 | O44: 0 | P44: 0 | Q44: 0 | R44: 0 | S44: 0 | T44: 0 | U44: 0 | V44: 0 | W44: 0 | X44: 0 | Y44: 0 | Z44: 0 | AA44: 0 | AB44: 0 | AC44: 0 | AD44: 0 | AE44: 0 | AF44: 0 | AG44: 0 | AH44: 0 | AI44: 0 | AJ44: 0 | AK44: 0 | AL44: 0 | AM44: 0 | AN44: 0 | AO44: 0 | AP44: 0 | AQ44: 0 | AR44: 0 | AS44: 0 | AT44: 0 | AU44: 1170000000 | AV44: 0 | AW44: 0 | AX44: 0 | AY44: 0 | AZ44: 0 | BA44: 0 | BB44: 0 | BC44: 0 | BD44: 0 | BE44: 0 | BF44: 0 | BG44: 0 | BH44: 0 | BI44: 0
A45: Contabilidad ITALO | B45: 740000 | C45: 740000 | D45: 740000 | E45: 740000 | F45: 740000 | G45: 740000 | H45: 740000 | I45: 740000 | J45: 740000 | K45: 740000 | L45: 740000 | M45: 740000 | N45: 740000 | O45: 740000 | P45: 740000 | Q45: 740000 | R45: 740000 | S45: 740000 | T45: 740000 | U45: 740000 | V45: 740000 | W45: 740000 | X45: 740000 | Y45: 740000 | Z45: 740000 | AA45: 740000
A46: Contabilidad Tributaria LENA | B46: 550000 | C46: 550000 | D46: 550000 | E46: 550000 | F46: 550000 | G46: 550000 | H46: 550000 | I46: 550000 | J46: 550000 | K46: 550000 | L46: 550000 | M46: 550000 | N46: 550000 | O46: 550000 | P46: 550000 | Q46: 550000 | R46: 550000 | S46: 550000 | T46: 550000 | U46: 550000 | V46: 550000 | W46: 700000 | X46: 700000 | Y46: 700000 | Z46: 700000 | AA46: 700000 | AB46: 700000 | AC46: 700000 | AD46: 700000 | AE46: 700000 | AF46: 700000 | AG46: 700000 | AH46: 700000 | AI46: 700000 | AJ46: 700000 | AK46: 700000 | AL46: 700000 | AM46: 700000 | AN46: 700000 | AO46: 700000 | AP46: 700000 | AQ46: 700000 | AR46: 700000 | AS46: 700000 | AT46: 700000 | AU46: 700000 | AV46: 700000 | AW46: 700000 | AX46: 700000 | AY46: 700000 | AZ46: 700000 | BA46: 700000 | BB46: 700000 | BC46: 700000 | BD46: 700000 | BE46: 700000 | BF46: 700000 | BG46: 700000 | BH46: 700000 | BI46: 700000
A47: CONTRATOS PREVER O AZOCAR FALLECIMIENTO | B47: 0 | C47: 0 | D47: 0 | E47: 0 | F47: 0 | G47: 0 | H47: 0 | I47: 0 | J47: 0 | K47: 0 | L47: 0 | M47: 0 | N47: 0 | O47: 0 | P47: 0 | Q47: 0 | R47: 0 | S47: 0 | T47: 0 | U47: 0 | V47: 0 | W47: 0 | X47: 0 | Y47: 0 | Z47: 0 | AA47: 0 | AB47: 0 | AC47: 0 | AD47: 0 | AE47: 0 | AF47: 0 | AG47: 0 | AH47: 0 | AI47: 0 | AJ47: 0 | AK47: 0 | AL47: 0 | AM47: 0 | AN47: 0 | AO47: 0 | AP47: 0 | AQ47: 0 | AR47: 0 | AS47: 0 | AT47: 0 | AU47: 0 | AV47: 0 | AW47: 0 | AX47: 0 | AY47: 0 | AZ47: 0 | BA47: 0 | BB47: 0 | BC47: 0 | BD47: 0 | BE47: 0 | BF47: 0 | BG47: 0 | BH47: 0 | BI47: 0
A48: CONTRIBUCIONES CASA | B48: 0 | C48: 3717000 | D48: 0 | E48: 3717000 | F48: 0 | G48: 0 | H48: 0 | I48: 0 | J48: 3717000 | K48: 0 | L48: 3717000 | M48: 0 | N48: 0 | O48: 3717000 | P48: 0 | Q48: 3717000 | R48: 0 | S48: 0 | T48: 0 | U48: 0 | V48: 3717000 | W48: 0 | X48: 3717000 | Y48: 0 | Z48: 0 | AA48: 3800000 | AB48: 0 | AC48: 3800000 | AD48: 0 | AE48: 0 | AF48: 0 | AG48: 0 | AH48: 3717000 | AI48: 0 | AJ48: 3717000 | AK48: 0 | AL48: 0 | AM48: 3717000 | AN48: 0 | AO48: 3717000 | AP48: 0 | AQ48: 3717000 | AR48: 0 | AS48: 0 | AT48: 0 | AU48: 0 | AV48: 0 | AW48: 0 | AX48: 0 | AY48: 0 | AZ48: 0 | BA48: 0 | BB48: 0 | BC48: 0 | BD48: 0 | BE48: 0 | BF48: 0 | BG48: 0 | BH48: 0 | BI48: 0
A49: CONTRIBUCIONES NUEVA CASA | B49: 0 | C49: 0 | D49: 0 | E49: 0 | F49: 0 | G49: 0 | H49: 0 | I49: 0 | J49: 0 | K49: 0 | L49: 0 | M49: 0 | N49: 0 | O49: 0 | P49: 0 | Q49: 0 | R49: 0 | S49: 0 | T49: 0 | U49: 0 | V49: 0 | W49: 0 | X49: 0 | Y49: 0 | Z49: 0 | AA49: 0 | AB49: 0 | AC49: 0 | AD49: 0 | AE49: 0 | AF49: 0 | AG49: 0 | AH49: 0 | AI49: 0 | AJ49: 0 | AK49: 0 | AL49: 0 | AM49: 0 | AN49: 0 | AO49: 0 | AP49: 0 | AQ49: 0 | AR49: 0 | AS49: 0 | AT49: 1858500 | AU49: 0 | AV49: 1858500 | AW49: 0 | AX49: 0 | AY49: 1858500 | AZ49: 0 | BA49: 1858500 | BB49: 0 | BC49: 0 | BD49: 0 | BE49: 0 | BF49: 1858500 | BG49: 0 | BH49: 1858500 | BI49: 0
A50: CONTRIBUCIONES PICHILEMU | B50: 0 | C50: 0 | D50: 0 | E50: 0 | F50: 0 | G50: 0 | H50: 0 | I50: 0 | J50: 0 | K50: 0 | L50: 0 | M50: 0 | N50: 0 | O50: 0 | P50: 0 | Q50: 0 | R50: 0 | S50: 0 | T50: 0 | U50: 0 | V50: 0 | W50: 0 | X50: 0 | Y50: 0 | Z50: 0 | AA50: 0 | AB50: 0 | AC50: 0 | AD50: 0 | AE50: 0 | AF50: 0 | AG50: 0 | AH50: 0 | AI50: 0 | AJ50: 0 | AK50: 0 | AL50: 0 | AM50: 0 | AN50: 0 | AO50: 0 | AP50: 0 | AQ50: 0 | AR50: 0 | AS50: 0 | AT50: 0 | AU50: 0 | AV50: 0 | AW50: 0 | AX50: 0 | AY50: 0 | AZ50: 0 | BA50: 0 | BB50: 0 | BC50: 0 | BD50: 0 | BE50: 0 | BF50: 0 | BG50: 0 | BH50: 0 | BI50: 0
A51: CONTRIBUCIONES Y DERECHOS DE ASEO PROPIEDADES DE RENTA | B51: 0 | C51: 333708 | D51: 0 | E51: 333708 | F51: 0 | G51: 0 | H51: 0 | I51: 0 | J51: 333708 | K51: 0 | L51: 333708 | M51: 0 | N51: 0 | O51: 333708 | P51: 0 | Q51: 333708 | R51: 0 | S51: 0 | T51: 0 | U51: 0 | V51: 333708 | W51: 0 | X51: 333708 | Y51: 0 | Z51: 0 | AA51: 333708 | AB51: 0 | AC51: 333708 | AD51: 0 | AE51: 0 | AF51: 0 | AG51: 0 | AH51: 333708 | AI51: 0 | AJ51: 333708 | AK51: 0 | AL51: 0 | AM51: 333708 | AN51: 0 | AO51: 333708 | AP51: 0 | AQ51: 333708 | AR51: 0 | AS51: 0 | AT51: 333708 | AU51: 0 | AV51: 333708 | AW51: 0 | AX51: 0 | AY51: 333708 | AZ51: 0 | BA51: 333708 | BB51: 0 | BC51: 0 | BD51: 0 | BE51: 0 | BF51: 333708 | BG51: 0 | BH51: 333708 | BI51: 0
A52: DIVIDENDOS CONSTANTINO | B52: 2240854 | C52: 2240854 | D52: 2240854 | E52: 2240854 | F52: 2240854 | G52: 2240854 | H52: 2240854 | I52: 2240854 | J52: 2240854 | K52: 2240854 | L52: 2240854 | M52: 2240854 | N52: 2240854 | O52: 2240854 | P52: 2240854 | Q52: 2240854 | R52: 2240854 | S52: 2240854 | T52: 2240854 | U52: 2240854 | V52: 2240854 | W52: 2240854 | X52: 2240854 | Y52: 2240854 | Z52: 2240854 | AA52: 2240854 | AB52: 2240854 | AC52: 2240854 | AD52: 2240854 | AE52: 2240854 | AF52: 2240854 | AG52: 2240854 | AH52: 2240854 | AI52: 2240854 | AJ52: 2240854 | AK52: 2240854 | AL52: 2240854 | AM52: 2240854 | AN52: 2240854 | AO52: 2240854 | AP52: 2240854 | AQ52: 2240854 | AR52: 2240854 | AS52: 2240854 | AT52: 2240854 | AU52: 2240854 | AV52: 2240854 | AW52: 2240854 | AX52: 2240854 | AY52: 2240854 | AZ52: 2240854 | BA52: 2240854 | BB52: 2240854 | BC52: 2240854 | BD52: 2240854 | BE52: 2240854 | BF52: 2240854 | BG52: 2240854 | BH52: 2240854 | BI52: 2240854
A53: DOCTORES | B53: 700000 | C53: 700000 | D53: 700000 | E53: 700000 | F53: 700000 | G53: 700000 | H53: 700000 | I53: 700000 | J53: 700000 | K53: 700000 | L53: 700000 | M53: 700000 | N53: 700000 | O53: 700000 | P53: 700000 | Q53: 700000 | R53: 700000 | S53: 700000 | T53: 700000 | U53: 700000 | V53: 700000 | W53: 700000 | X53: 700000 | Y53: 700000 | Z53: 700000 | AA53: 700000 | AB53: 700000 | AC53: 700000 | AD53: 700000 | AE53: 700000 | AF53: 700000 | AG53: 700000 | AH53: 700000 | AI53: 700000 | AJ53: 700000 | AK53: 700000 | AL53: 700000 | AM53: 700000 | AN53: 700000 | AO53: 700000 | AP53: 700000 | AQ53: 700000 | AR53: 700000 | AS53: 700000 | AT53: 700000 | AU53: 700000 | AV53: 700000 | AW53: 700000 | AX53: 700000 | AY53: 700000 | AZ53: 700000 | BA53: 700000 | BB53: 700000 | BC53: 700000 | BD53: 700000 | BE53: 700000 | BF53: 700000 | BG53: 700000 | BH53: 700000 | BI53: 700000
A54: GAS | B54: 44000 | C54: 44000 | D54: 44000 | E54: 44000 | F54: 40000 | G54: 40000 | H54: 40000 | I54: 40000 | J54: 40000 | K54: 40000 | L54: 40000 | M54: 40000 | N54: 40000 | O54: 40000 | P54: 40000 | Q54: 40000 | R54: 40000 | S54: 40000 | T54: 40000 | U54: 40000 | V54: 40000 | W54: 40000 | X54: 40000 | Y54: 40000 | Z54: 40000 | AA54: 40000 | AB54: 40000 | AC54: 40000 | AD54: 40000 | AE54: 100000 | AF54: 100000 | AG54: 100000 | AH54: 100000 | AI54: 100000 | AJ54: 100000 | AK54: 100000 | AL54: 100000 | AM54: 100000 | AN54: 100000 | AO54: 100000 | AP54: 100000 | AQ54: 100000 | AR54: 100000 | AS54: 100000 | AT54: 100000 | AU54: 100000 | AV54: 100000 | AW54: 100000 | AX54: 100000 | AY54: 100000 | AZ54: 100000 | BA54: 100000 | BB54: 100000 | BC54: 100000 | BD54: 100000 | BE54: 100000 | BF54: 100000 | BG54: 100000 | BH54: 100000 | BI54: 100000
A55: GASTOS CASA SANTUARIO PARA VENTA | B55: 0 | C55: 0 | D55: 0 | E55: 0 | F55: 0 | G55: 0 | H55: 0 | I55: 0 | J55: 0 | K55: 0 | L55: 0 | M55: 0 | N55: 0 | O55: 0 | P55: 0 | Q55: 0 | R55: 0 | S55: 0 | Z55: 1200000 | AA55: 1200000 | AB55: 1200000 | AC55: 1200000 | AD55: 1200000 | AE55: 1200000 | AF55: 1200000 | AG55: 1200000 | AH55: 1200000 | AI55: 1200000 | AJ55: 1200000 | AK55: 1200000 | AL55: 1200000 | AM55: 1200000 | AN55: 1200000 | AO55: 1200000 | AP55: 1200000 | AQ55: 1200000 | AR55: 1200000 | AS55: 0 | AT55: 0 | AU55: 0 | AV55: 0 | AW55: 0 | AX55: 0 | AY55: 0 | AZ55: 0 | BA55: 0 | BB55: 0 | BC55: 0 | BD55: 0 | BE55: 0 | BF55: 0 | BG55: 0 | BH55: 0 | BI55: 0
A56: GASTOS COMUNES LA LUMA | B56: 880000 | C56: 880000 | D56: 880000 | E56: 880000 | F56: 880000 | G56: 880000 | H56: 880000 | I56: 880000 | J56: 880000 | K56: 880000 | L56: 880000 | M56: 880000 | N56: 880000 | O56: 880000 | P56: 880000 | Q56: 880000 | R56: 880000 | S56: 880000 | T56: 0 | U56: 0 | V56: 0 | W56: 0 | X56: 0 | Y56: 0 | Z56: 0 | AA56: 0 | AB56: 0 | AC56: 0 | AD56: 0 | AE56: 0 | AF56: 0 | AG56: 0 | AH56: 0 | AI56: 0 | AJ56: 0 | AK56: 0 | AL56: 0 | AM56: 0 | AN56: 0 | AO56: 0 | AP56: 0 | AQ56: 0 | AR56: 0 | AS56: 880000 | AT56: 880000 | AU56: 880000 | AV56: 880000 | AW56: 880000 | AX56: 880000 | AY56: 880000 | AZ56: 880000 | BA56: 880000 | BB56: 880000 | BC56: 880000 | BD56: 880000 | BE56: 880000 | BF56: 880000 | BG56: 880000 | BH56: 880000 | BI56: 880000
A57: COMISIONES PROPIEDAES | B57: 100000 | C57: 100000 | D57: 100000 | E57: 100000 | F57: 100000 | G57: 100000 | H57: 100000 | I57: 100000 | J57: 100000 | K57: 100000 | L57: 100000 | M57: 100000 | N57: 100000 | O57: 100000 | P57: 100000 | Q57: 100000 | R57: 100000 | S57: 100000 | T57: 0 | U57: 0 | V57: 0 | W57: 0 | X57: 0 | Y57: 0 | Z57: 0 | AA57: 0 | AB57: 0 | AC57: 0 | AD57: 0 | AE57: 0 | AF57: 0 | AG57: 0 | AH57: 0 | AI57: 0 | AJ57: 0 | AK57: 0 | AL57: 0 | AM57: 0 | AN57: 0 | AO57: 0 | AP57: 0 | AQ57: 0 | AR57: 0 | AS57: 100000 | AT57: 100000 | AU57: 100000 | AV57: 100000 | AW57: 100000 | AX57: 100000 | AY57: 100000 | AZ57: 100000 | BA57: 100000 | BB57: 100000 | BC57: 100000 | BD57: 100000 | BE57: 100000 | BF57: 100000 | BG57: 100000 | BH57: 100000 | BI57: 100000
A58: CONTABILIDAD BAKER | B58: 650000 | C58: 650000 | D58: 650000 | E58: 650000 | F58: 650000 | G58: 650000 | H58: 650000 | I58: 650000 | J58: 650000 | K58: 650000 | L58: 650000 | M58: 650000 | N58: 650000 | O58: 650000 | P58: 650000 | Q58: 650000 | R58: 650000 | S58: 650000 | T58: 0 | U58: 0 | V58: 0 | W58: 0 | X58: 0 | Y58: 0 | Z58: 0 | AA58: 0 | AB58: 0 | AC58: 0 | AD58: 0 | AE58: 0 | AF58: 0 | AG58: 0 | AH58: 0 | AI58: 0 | AJ58: 0 | AK58: 0 | AL58: 0 | AM58: 0 | AN58: 0 | AO58: 0 | AP58: 0 | AQ58: 0 | AR58: 0 | AS58: 650000 | AT58: 650000 | AU58: 650000 | AV58: 650000 | AW58: 650000 | AX58: 650000 | AY58: 650000 | AZ58: 650000 | BA58: 650000 | BB58: 650000 | BC58: 650000 | BD58: 650000 | BE58: 650000 | BF58: 650000 | BG58: 650000 | BH58: 650000 | BI58: 650000
A59: GASTOS COMUNES Y ARREGLOS PROPIEDADES DE RENTA | B59: 120000 | C59: 120000 | D59: 120000 | E59: 120000 | F59: 120000 | G59: 120000 | H59: 120000 | I59: 120000 | J59: 120000 | K59: 120000 | L59: 120000 | M59: 120000 | N59: 120000 | O59: 120000 | P59: 120000 | Q59: 120000 | R59: 120000 | S59: 120000 | T59: 0 | U59: 0 | V59: 0 | W59: 0 | X59: 0 | Y59: 0 | Z59: 0 | AA59: 0 | AB59: 0 | AC59: 0 | AD59: 0 | AE59: 0 | AF59: 0 | AG59: 0 | AH59: 0 | AI59: 0 | AJ59: 0 | AK59: 0 | AL59: 0 | AM59: 0 | AN59: 0 | AO59: 0 | AP59: 0 | AQ59: 0 | AR59: 0 | AS59: 120000 | AT59: 0 | AU59: 0 | AV59: 0 | AW59: 0 | AX59: 0 | AY59: 0 | AZ59: 0 | BA59: 0 | BB59: 0 | BC59: 0 | BD59: 0 | BE59: 0 | BF59: 0 | BG59: 0 | BH59: 0 | BI59: 0
A60: HOSPITALIZACIONES
A61: HONORARIOS JUICIO VILLABLANCA | B61: 800000 | C61: 800000 | D61: 800000 | E61: 800000 | F61: 800000 | G61: 0 | H61: 0 | I61: 0 | J61: 0 | K61: 0 | L61: 0 | M61: 0 | N61: 0 | O61: 0 | P61: 0 | Q61: 0 | R61: 0 | S61: 0 | T61: 0 | U61: 0 | V61: 0 | W61: 0 | X61: 0 | Y61: 0 | Z61: 0 | AA61: 0 | AB61: 0 | AC61: 0 | AD61: 0 | AE61: 0 | AF61: 0 | AG61: 0 | AH61: 0 | AI61: 0 | AJ61: 0 | AK61: 0 | AL61: 0 | AM61: 0 | AN61: 0 | AO61: 0 | AP61: 0 | AQ61: 0 | AR61: 0 | AS61: 0 | AT61: 0 | AU61: 0 | AV61: 0 | AW61: 0 | AX61: 0 | AY61: 0 | AZ61: 0 | BA61: 0 | BB61: 0 | BC61: 0 | BD61: 0 | BE61: 0 | BF61: 0 | BG61: 0 | BH61: 0 | BI61: 0
A62: IMPUESTOS | B62: 700000 | C62: 700000 | D62: 700000 | E62: 700000 | F62: 700000 | G62: 700000 | H62: 700000 | I62: 700000 | J62: 700000 | K62: 700000 | L62: 700000 | M62: 700000 | N62: 700000 | O62: 700000 | P62: 700000 | Q62: 700000 | R62: 700000 | S62: 700000 | T62: 700000 | U62: 700000 | V62: 700000 | W62: 700000 | X62: 700000 | Y62: 700000 | Z62: 700000 | AA62: 700000 | AB62: 700000 | AC62: 700000 | AD62: 700000 | AE62: 700000 | AF62: 700000 | AG62: 700000 | AH62: 700000 | AI62: 700000 | AJ62: 700000 | AK62: 700000 | AL62: 700000 | AM62: 700000 | AN62: 700000 | AO62: 700000 | AP62: 700000 | AQ62: 700000 | AR62: 700000 | AS62: 700000 | AT62: 700000 | AU62: 700000 | AV62: 700000 | AW62: 700000 | AX62: 700000 | AY62: 700000 | AZ62: 700000 | BA62: 700000 | BB62: 700000 | BC62: 700000 | BD62: 700000 | BE62: 700000 | BF62: 700000 | BG62: 700000 | BH62: 700000 | BI62: 700000
A63: ISAPRES | B63: 450000 | C63: 450000 | D63: 450000 | E63: 450000 | F63: 450000 | G63: 490000 | H63: 490000 | I63: 490000 | J63: 490000 | K63: 490000 | L63: 490000 | M63: 490000 | N63: 490000 | O63: 490000 | P63: 490000 | Q63: 490000 | R63: 490000 | S63: 490000 | T63: 490000 | U63: 490000 | V63: 490000 | W63: 490000 | X63: 490000 | Y63: 490000 | Z63: 490000 | AA63: 490000 | AB63: 490000 | AC63: 490000 | AD63: 490000 | AE63: 490000 | AF63: 490000 | AG63: 490000 | AH63: 490000 | AI63: 490000 | AJ63: 490000 | AK63: 490000 | AL63: 490000 | AM63: 490000 | AN63: 490000 | AO63: 490000 | AP63: 490000 | AQ63: 490000 | AR63: 490000 | AS63: 490000 | AT63: 490000 | AU63: 490000 | AV63: 490000 | AW63: 490000 | AX63: 490000 | AY63: 490000 | AZ63: 490000 | BA63: 490000 | BB63: 490000 | BC63: 490000 | BD63: 490000 | BE63: 490000 | BF63: 490000 | BG63: 490000 | BH63: 490000 | BI63: 490000
A64: LUZ | B64: 276100 | C64: 276100 | D64: 276100 | E64: 276100 | F64: 135000 | G64: 135000 | H64: 135000 | I64: 135000 | J64: 135000 | K64: 135000 | L64: 135000 | M64: 135000 | N64: 135000 | O64: 135000 | P64: 135000 | Q64: 135000 | R64: 135000 | S64: 135000 | T64: 135000 | U64: 135000 | V64: 135000 | W64: 135000 | X64: 135000 | Y64: 135000 | Z64: 135000 | AA64: 135000 | AB64: 135000 | AC64: 135000 | AD64: 135000 | AE64: 135000 | AF64: 135000 | AG64: 135000 | AH64: 135000 | AI64: 135000 | AJ64: 135000 | AK64: 135000 | AL64: 135000 | AM64: 135000 | AN64: 135000 | AO64: 135000 | AP64: 135000 | AQ64: 135000 | AR64: 135000 | AS64: 135000 | AT64: 135000 | AU64: 135000 | AV64: 135000 | AW64: 135000 | AX64: 135000 | AY64: 135000 | AZ64: 135000 | BA64: 135000 | BB64: 135000 | BC64: 135000 | BD64: 135000 | BE64: 135000 | BF64: 135000 | BG64: 135000 | BH64: 135000 | BI64: 135000
A65: COSTO DE MATRIMONIOS TODO | B65: 0 | C65: 0 | D65: 0 | E65: 0 | F65: 0 | G65: 0 | H65: 0 | I65: 0 | J65: 0 | K65: 0 | L65: 0 | M65: 0 | N65: 27000000 | O65: 0 | P65: 0 | Q65: 0 | R65: 0 | S65: 27000000 | T65: 0 | U65: 0 | V65: 0 | W65: 0 | X65: 0 | Y65: 0 | Z65: 0 | AA65: 0 | AB65: 0 | AC65: 0 | AD65: 0 | AE65: 0 | AF65: 0 | AG65: 0 | AH65: 0 | AI65: 0 | AJ65: 0 | AK65: 0 | AL65: 0 | AM65: 0 | AN65: 0 | AO65: 0 | AP65: 0 | AQ65: 0 | AR65: 0 | AS65: 0 | AT65: 0 | AU65: 0 | AV65: 0 | AW65: 0 | AX65: 0 | AY65: 0 | AZ65: 0 | BA65: 0 | BB65: 0 | BC65: 0 | BD65: 0 | BE65: 0 | BF65: 0 | BG65: 0 | BH65: 0 | BI65: 0
A66: PAGO MENSUAL TUMBA ZAPALLAR CUOTAS Y MANTENCION | B66: 200000 | C66: 200000 | D66: 200000 | E66: 200000 | F66: 200000 | G66: 200000 | H66: 200000 | I66: 200000 | J66: 200000 | K66: 200000 | L66: 250000 | M66: 200000 | N66: 200000 | O66: 200000 | P66: 0 | Q66: 0 | R66: 0 | S66: 0 | T66: 0 | U66: 0 | V66: 0 | W66: 0 | X66: 50000 | Y66: 0 | Z66: 0 | AA66: 0 | AB66: 0 | AC66: 0 | AD66: 0 | AE66: 0 | AF66: 0 | AG66: 0 | AH66: 0 | AI66: 0 | AJ66: 50000 | AK66: 0 | AL66: 0 | AM66: 0 | AN66: 0 | AO66: 0 | AP66: 0 | AQ66: 0 | AR66: 0 | AS66: 0 | AT66: 0 | AU66: 0 | AV66: 50000 | AW66: 0 | AX66: 0 | AY66: 0 | AZ66: 0 | BA66: 0 | BB66: 0 | BC66: 0 | BD66: 0 | BE66: 0 | BF66: 0 | BG66: 0 | BH66: 50000 | BI66: 0
A67: OCIO
A68: HONORARIOS FO | B68: 1000000 | C68: 1000000 | D68: 1000000 | E68: 1000000 | F68: 1000000 | G68: 1000000 | H68: 1000000 | I68: 1000000 | J68: 1000000 | K68: 1000000 | L68: 1000000 | M68: 1000000 | N68: 1000000 | O68: 1000000 | P68: 1000000 | Q68: 1000000 | R68: 1000000 | S68: 1000000 | T68: 1000000 | U68: 1000000 | V68: 1000000 | W68: 1000000 | X68: 1000000 | Y68: 1000000 | Z68: 1000000 | AA68: 1000000 | AB68: 1000000 | AC68: 1000000 | AD68: 1000000 | AE68: 1000000 | AF68: 1000000 | AG68: 1000000 | AH68: 1000000 | AI68: 1000000 | AJ68: 1000000 | AK68: 1000000 | AL68: 1000000 | AM68: 1000000 | AN68: 1000000 | AO68: 1000000 | AP68: 1000000 | AQ68: 1000000 | AR68: 1000000 | AS68: 1000000 | AT68: 1000000 | AU68: 1000000 | AV68: 1000000 | AW68: 1000000 | AX68: 1000000 | AY68: 1000000 | AZ68: 1000000 | BA68: 1000000 | BB68: 1000000 | BC68: 1000000 | BD68: 1000000 | BE68: 1000000 | BF68: 1000000 | BG68: 1000000 | BH68: 1000000 | BI68: 1000000
A69: VIAJES Y VACACIONES
A70: PATENTES AUTOS REVISIONES TECNICAS (1,4 mm año) | B70: 0 | C70: 0 | D70: 0 | E70: 0 | F70: 0 | G70: 0 | H70: 0 | I70: 1400000 | J70: 0 | K70: 0 | L70: 0 | M70: 0 | N70: 0 | O70: 0 | P70: 0 | Q70: 0 | R70: 0 | S70: 0 | T70: 0 | U70: 500000 | V70: 0 | W70: 0 | X70: 0 | Y70: 0 | Z70: 0 | AA70: 0 | AB70: 0 | AC70: 0 | AD70: 0 | AE70: 0 | AF70: 0 | AG70: 500000 | AH70: 0 | AI70: 0 | AJ70: 0 | AK70: 0 | AL70: 0 | AM70: 0 | AN70: 0 | AO70: 0 | AP70: 0 | AQ70: 0 | AR70: 0 | AS70: 500000 | AT70: 0 | AU70: 0 | AV70: 0 | AW70: 0 | AX70: 0 | AY70: 0 | AZ70: 0 | BA70: 0 | BB70: 0 | BC70: 0 | BD70: 0 | BE70: 500000 | BF70: 0 | BG70: 0 | BH70: 0 | BI70: 0
A71: PATENTES COMERCIALES + Direccion fiscal (Preguntar a ITALO) UF | G71: 9580321
A72: CUOTAS MENSUALES CLUB DE POLO (UF) | B72: 507234 | C72: 507234 | D72: 507234 | E72: 507234 | F72: 507234 | G72: 435000 | H72: 435000 | I72: 435000 | J72: 435000 | K72: 435000 | L72: 435000 | M72: 435000 | N72: 435000 | O72: 435000 | P72: 435000 | Q72: 435000 | R72: 435000 | S72: 435000 | T72: 435000 | U72: 435000 | V72: 435000 | W72: 435000 | X72: 435000 | Y72: 435000 | Z72: 435000 | AA72: 435000 | AB72: 435000 | AC72: 435000 | AD72: 435000 | AE72: 435000 | AF72: 435000 | AG72: 435000 | AH72: 435000 | AI72: 435000 | AJ72: 435000 | AK72: 435000 | AL72: 435000 | AM72: 435000 | AN72: 435000 | AO72: 435000 | AP72: 435000 | AQ72: 435000 | AR72: 435000 | AS72: 435000 | AT72: 435000 | AU72: 435000 | AV72: 435000 | AW72: 435000 | AX72: 435000 | AY72: 435000 | AZ72: 435000 | BA72: 435000 | BB72: 435000 | BC72: 435000 | BD72: 435000 | BE72: 435000 | BF72: 435000 | BG72: 435000 | BH72: 435000 | BI72: 435000
A73: FARMACIA | B73: 400000 | C73: 400000 | D73: 400000 | E73: 400000 | F73: 400000 | G73: 400000 | H73: 400000 | I73: 400000 | J73: 400000 | K73: 400000 | L73: 400000 | M73: 400000 | N73: 400000 | O73: 400000 | P73: 400000 | Q73: 400000 | R73: 400000 | S73: 400000 | T73: 400000 | U73: 400000 | V73: 400000 | W73: 400000 | X73: 400000 | Y73: 400000 | Z73: 400000 | AA73: 400000 | AB73: 400000 | AC73: 400000 | AD73: 400000 | AE73: 400000 | AF73: 400000 | AG73: 400000 | AH73: 400000 | AI73: 400000 | AJ73: 400000 | AK73: 400000 | AL73: 400000 | AM73: 400000 | AN73: 400000 | AO73: 400000 | AP73: 400000 | AQ73: 400000 | AR73: 400000 | AS73: 400000 | AT73: 400000 | AU73: 400000 | AV73: 400000 | AW73: 400000 | AX73: 400000 | AY73: 400000 | AZ73: 400000 | BA73: 400000 | BB73: 400000 | BC73: 400000 | BD73: 400000 | BE73: 400000 | BF73: 400000 | BG73: 400000 | BH73: 400000 | BI73: 400000
A74: RETIROS EMPRESAS | B74: 4023392 | C74: 4023392 | D74: 4023392 | E74: 4023392 | F74: 4023392 | G74: 4023392 | H74: 4023392 | I74: 4023392 | J74: 4023392 | K74: 4023392 | L74: 4023392 | M74: 4023392 | N74: 4023392 | O74: 4023392 | P74: 4023392 | Q74: 4023392 | R74: 4023392 | S74: 4023392 | T74: 4023392 | U74: 4023392 | V74: 4023392 | W74: 4023392 | X74: 4023392 | Y74: 4023392 | Z74: 4023392 | AA74: 4023392 | AB74: 4023392 | AC74: 4023392 | AD74: 4023392 | AE74: 4023392 | AF74: 4023392 | AG74: 4023392 | AH74: 4023392 | AI74: 4023392 | AJ74: 4023392 | AK74: 4023392 | AL74: 4023392 | AM74: 4023392 | AN74: 4023392 | AO74: 4023392 | AP74: 4023392 | AQ74: 4023392 | AR74: 4023392 | AS74: 4023392 | AT74: 4023392 | AU74: 4023392 | AV74: 4023392 | AW74: 4023392 | AX74: 4023392 | AY74: 4023392 | AZ74: 4023392 | BA74: 4023392 | BB74: 4023392 | BC74: 4023392 | BD74: 4023392 | BE74: 4023392 | BF74: 4023392 | BG74: 4023392 | BH74: 4023392 | BI74: 4023392
A75: SEGUROS DE VIDA Y COMPLEMENTARIO CLINICA LAS CONDES | B75: 700000 | C75: 700000 | D75: 700000 | E75: 700000 | F75: 700000 | G75: 700000 | H75: 700000 | I75: 700000 | J75: 700000 | K75: 700000 | L75: 700000 | M75: 700000 | N75: 700000 | O75: 700000 | P75: 700000 | Q75: 700000 | R75: 700000 | S75: 700000 | T75: 700000 | U75: 700000 | V75: 700000 | W75: 700000 | X75: 700000 | Y75: 700000 | Z75: 700000 | AA75: 700000 | AB75: 700000 | AC75: 700000 | AD75: 700000 | AE75: 700000 | AF75: 700000 | AG75: 700000 | AH75: 700000 | AI75: 700000 | AJ75: 700000 | AK75: 700000 | AL75: 700000 | AM75: 700000 | AN75: 700000 | AO75: 700000 | AP75: 700000 | AQ75: 700000 | AR75: 700000 | AS75: 700000 | AT75: 700000 | AU75: 700000 | AV75: 700000 | AW75: 700000 | AX75: 700000 | AY75: 700000 | AZ75: 700000 | BA75: 700000 | BB75: 700000 | BC75: 700000 | BD75: 700000 | BE75: 700000 | BF75: 700000 | BG75: 700000 | BH75: 700000 | BI75: 700000
A76: SEGUROS AUTOS CAM AGOSTO, PAR OCTUBRE (UF) | B76: 599928 | C76: 0 | D76: 398377 | E76: 0 | F76: 0 | G76: 0 | H76: 0 | I76: 0 | J76: 0 | K76: 0 | L76: 0 | M76: 0 | N76: 599928 | O76: 0 | P76: 398377 | Q76: 0 | R76: 0 | S76: 0 | T76: 0 | U76: 0 | V76: 0 | W76: 0 | X76: 0 | Y76: 0 | Z76: 599928 | AA76: 0 | AB76: 398377 | AC76: 0 | AD76: 0 | AE76: 0 | AF76: 0 | AG76: 0 | AH76: 0 | AI76: 0 | AJ76: 0 | AK76: 0 | AL76: 599928 | AM76: 0 | AN76: 398377 | AO76: 0 | AP76: 0 | AQ76: 0 | AR76: 0 | AS76: 0 | AT76: 0 | AU76: 0 | AV76: 0 | AW76: 0 | AX76: 599928 | AY76: 0 | AZ76: 398377 | BA76: 0 | BB76: 0 | BC76: 0 | BD76: 0 | BE76: 0 | BF76: 0 | BG76: 0 | BH76: 0 | BI76: 0
A77: TAGS | B77: 90000 | C77: 90000 | D77: 90000 | E77: 90000 | F77: 90000 | G77: 90000 | H77: 90000 | I77: 90000 | J77: 70000 | K77: 70000 | L77: 70000 | M77: 70000 | N77: 70000 | O77: 70000 | P77: 70000 | Q77: 70000 | R77: 70000 | S77: 70000 | T77: 70000 | U77: 70000 | V77: 70000 | W77: 70000 | X77: 70000 | Y77: 70000 | Z77: 70000 | AA77: 70000 | AB77: 70000 | AC77: 70000 | AD77: 70000 | AE77: 70000 | AF77: 70000 | AG77: 70000 | AH77: 70000 | AI77: 70000 | AJ77: 70000 | AK77: 70000 | AL77: 70000 | AM77: 70000 | AN77: 70000 | AO77: 70000 | AP77: 70000 | AQ77: 70000 | AR77: 70000 | AS77: 70000 | AT77: 70000 | AU77: 70000 | AV77: 70000 | AW77: 70000 | AX77: 70000 | AY77: 70000 | AZ77: 70000 | BA77: 70000 | BB77: 70000 | BC77: 70000 | BD77: 70000 | BE77: 70000 | BF77: 70000 | BG77: 70000 | BH77: 70000 | BI77: 70000
A78: OTROS
A79: Efecto Inflacion | B79: 620882 | C79: 672644 | D79: 617859 | E79: 672644 | F79: 609818 | G79: 609334 | H79: 609334 | I79: 616834 | J79: 759795 | K79: 609034 | L79: 670545 | M79: 609034 | N79: 1023033 | O79: 669795 | P79: 612010 | Q79: 666795 | R79: 606034 | S79: 1011034 | T79: 673834 | U79: 681334 | V79: 734595 | W79: 676834 | X79: 663345 | Y79: 600934 | Z79: 609933 | AA79: 737940 | AB79: 606910 | AC79: 662940 | AD79: 548434 | AE79: 550249 | AF79: 550249 | AG79: 557749 | AH79: 611010 | AI79: 547249 | AJ79: 608760 | AK79: 549499 | AL79: 556248 | AM79: 608010 | AN79: 553225 | AO79: 608010 | AP79: 547249 | AQ79: 608010 | AR79: 430138 | AS79: 408388 | AT79: 431971 | AU79: 17949088 | AV79: 427532 | AW79: 393899 | AX79: 402898 | AY79: 426782 | AZ79: 399875 | BA79: 426782 | BB79: 393899 | BC79: 393899 | BD79: 393899 | BE79: 398399 | BF79: 423782 | BG79: 390899 | BH79: 424532 | BI79: 465899
A80: TOTAL EGRESOS | B80: =SUM(B29:B79) -> 35845695 | C80: =SUM(C29:C79) -> 39348237 | D80: =SUM(D29:D79) -> 35641121 | E80: =SUM(E29:E79) -> 39348237 | F80: =SUM(F29:F79) -> 35097000 | G80: =SUM(G29:G79) -> 43844603 | H80: =SUM(H29:H79) -> 34264282 | I80: =SUM(I29:I79) -> 35671782 | ... BI80: =SUM(BI29:BI79) -> 19125945
A82: SALDO MENSUAL (Ingresos - Egresos) | B82: =B26-B80 -> 7511505.7 | C82: =C26-C80 -> 5695174.3 | D82: =D26-D80 -> 8642031.1 | E82: =E26-E80 -> 31695174 | F82: =F26-F80 -> 9822221.2 | G82: =G26-G80 -> -425381.76 | H82: =H26-H80 -> 9154939.2 | I82: =I26-I80 -> 24547439 | ... BI82: =BI26-BI80 -> 23414626
A83: Saldo Acumulado (según modelo original)
A85: ⚠ Revisar meses con Saldo Acumulado negativo (resaltados) antes de usar estas cifras en el dashboard — puede ser un compromiso de caja real o un artefacto del modelo original.
A87: RESUMEN ANUAL — MODELO 'FLUJO GENERAL' (oct de cada año, horizonte largo para KPIs a 10 años)
A88: Horizonte | B88: Total Ingresos | C88: Total Egresos | D88: Saldo Mensual | E88: Saldo Acumulado | F88: Activos Líquidos Totales (modelo)
A89: Año 0 (oct-2025, base) | B89: 36480426 | C89: 23202253 | D89: 13278174 | E89: 91978890 | F89: 2021055889
A90: Año 1 (oct-2026) | B90: 48290827 | C90: 30357671 | D90: 17933157 | E90: -1442977982 | F90: 1973395420
A91: Año 5 (oct-2030) | B91: 50494954 | C91: 27634249 | D91: 22860705 | E91: 166625417 | F91: 1849625541
A92: Año 10 (oct-2035) | B92: 50757902 | C92: 27395555 | D92: 23362347 | E92: -303081387 | F92: 1829631628

Sheet Balance_Consolidado
A1: BALANCE CONSOLIDADO — GRUPO FAMILIAR ARMAS ALVEAR
A2: Perímetro: núcleo + hijos · Todas las cifras enlazan a las pestañas de detalle (verde = fórmula entre pestañas)
A4: ACTIVOS
A5: Categoría | B5: Monto (CLP) | C5: % del Total | D5: Fuente
A6: Liquidez (perímetro familiar) | B6: =Liquidez!D33 -> 46044820 | C6: =B6/B$12 -> 0.0031438066 | D6: Pestaña Liquidez
A7: Inversiones Financieras (perímetro familiar) | B7: =Inversiones_Financieras!D38 -> 590887018 | C7: =B7/B$12 -> 0.04034405 | D7: Pestaña Inversiones_Financieras
A8: Cuentas por Cobrar operacionales | B8: =Otras_Partidas!B21 -> 80077240 | C8: =B8/B$12 -> 0.0054674415 | D8: Pestaña Otras_Partidas
A9: Otros activos menores | B9: =Otras_Partidas!B31 -> 39175638 | C9: =B9/B$12 -> 0.0026747988 | D9: Pestaña Otras_Partidas
A10: Bienes Raíces (Valor Atribuible) | B10: =Bienes_Raices!L39 -> 7.063315e+09 | C10: =B10/B$12 -> 0.48226265 | D10: Pestaña Bienes_Raices
A11: Empresas — Equity Value Estimado | B11: =Empresas!E39 -> 6826700000 | C11: =B11/B$12 -> 0.46610726 | D11: Pestaña Empresas
A12: TOTAL ACTIVOS | B12: =B6+B7+B8+B9+B10+B11 -> 1.46462e+10
A14: PASIVOS
A15: Categoría | B15: Monto (CLP) | C15: % del Total | D15: Fuente
A16: Patentes comerciales morosas | B16: =Pasivos!D10 -> 11742074 | D16: Pestaña Pasivos
A17: TOTAL PASIVOS | B17: =B16 -> 11742074
A19: PATRIMONIO NETO
A20: PATRIMONIO NETO (Activos - Pasivos) | B20: =B12-B17 -> 1.4634458e+10
A21: Memo: Activos Contingentes (no incluidos arriba) | B21: =Activos_Contingentes!B8 -> 180935763
A22: PATRIMONIO NETO AJUSTADO POR CONTINGENCIAS (memo) | B22: =B20+B21 -> 1.4815393e+10
A25: DISTRIBUCIÓN DE ACTIVOS POR CLASE
A26: Clase de Activo | B26: Monto (CLP) | C26: % del Total
A27: Liquidez | B27: =B6 -> 46044820 | C27: =B27/B$12 -> 0.0031438066
A28: Inversiones Financieras | B28: =B7 -> 590887018 | C28: =B28/B$12 -> 0.04034405
A29: Bienes Raíces | B29: =B10 -> 7.063315e+09 | C29: =B29/B$12 -> 0.48226265
A30: Empresas (Equity) | B30: =B11 -> 6826700000 | C30: =B30/B$12 -> 0.46610726
A31: Otros Activos (CxC + menores) | B31: =B8+B9 -> 119252878 | C31: =B31/B$12 -> 0.0081422403
A33: RENDIMIENTO ANUAL — POR CLASE DE ACTIVO
A34: Aún no hay serie histórica propia para calcular retorno realizado; se muestra el supuesto referencial de la pestaña Supuestos. Reemplazar por retorno observado cuando exista al menos 12 meses de valorización periódica.
A35: Clase de Activo | B35: Retorno Anual (supuesto) | C35: Tipo | D35: Fuente
A36: Liquidez | B36: =Supuestos!B10 -> 0.005 | C36: Supuesto (referencial) | D36: Pestaña Supuestos — reemplazar por retorno histórico real
A37: Inversiones Financieras | B37: =Supuestos!B11 -> 0.045 | C37: Supuesto (referencial) | D37: Pestaña Supuestos — reemplazar por retorno histórico real
A38: Bienes Raíces | B38: =Supuestos!B12 -> 0.03 | C38: Supuesto (referencial) | D38: Pestaña Supuestos — reemplazar por retorno histórico real
A39: Empresas (Equity operativo) | B39: =Supuestos!B13 -> 0.06 | C39: Supuesto (referencial) | D39: Pestaña Supuestos — reemplazar por retorno histórico real
A41: Nota: Bienes Raíces usa Tasación Comercial cuando está disponible; hoy usa Avalúo Fiscal x factor como proxy en las propiedades sin tasación real. Empresas usa Equity Value = % provisorio × Patrimonio Contable — la mayoría aún en $0 por falta de EEFF. El Patrimonio Neto real es mayor a esta cifra una vez se complete esa información.

Sheet KPIs
A1: KPIs — RENTABILIDAD, RIESGO Y BALANCE DEL PORTAFOLIO
A2: Horizontes: 1, 5 y 10 años. Combina el Balance_Consolidado (foto actual) con la proyección del modelo Flujo_Caja y los supuestos de retorno de la pestaña Supuestos.
A4: A. BALANCE Y ESTRUCTURA (foto actual)
A5: KPI | B5: Valor | E5: Fórmula / Fuente
A6: Total Activos | B6: =Balance_Consolidado!B12 -> 1.46462e+10 | E6: Balance_Consolidado
A7: Total Pasivos | B7: =Balance_Consolidado!B17 -> 11742074 | E7: Balance_Consolidado
A8: Patrimonio Neto | B8: =Balance_Consolidado!B20 -> 1.4634458e+10 | E8: Balance_Consolidado
A9: Apalancamiento (Pasivos / Activos) | B9: =B7/B6 -> 0.00080171472 | E9: Pasivos ÷ Activos — mientras más bajo, menor riesgo financiero
A10: Deuda / Patrimonio Neto | B10: =B7/B8 -> 0.00080235799 | E10: Pasivos ÷ Patrimonio Neto
A11: % del patrimonio en Liquidez | B11: =Balance_Consolidado!B6/B6 -> 0.0031438066 | E11: Liquidez ÷ Total Activos
A12: % del patrimonio en Bienes Raíces (concentración inmobiliaria) | B12: =Balance_Consolidado!B10/B6 -> 0.48226265 | E12: Bienes Raíces ÷ Total Activos — sobre 60-70% se considera alta concentración para un FO
A13: % del patrimonio en Empresas (equity operativo) | B13: =Balance_Consolidado!B11/B6 -> 0.46610726 | E13: Empresas ÷ Total Activos — subestimado hoy por falta de EEFF
A14: % del patrimonio en Inversiones Financieras líquidas | B14: =Balance_Consolidado!B7/B6 -> 0.04034405 | E14: Inversiones Financieras ÷ Total Activos
A15: Concentración — mayor propiedad individual | B15: =MAX(Bienes_Raices!L5:L38)/B6 -> 0.13943818 | E15: Mayor Valor Atribuible de una sola propiedad ÷ Total Activos
A17: B. LIQUIDEZ Y COBERTURA DE FLUJO
A18: KPI | B18: Valor | E18: Fórmula / Fuente
A19: Cobertura de gasto mensual (Ingresos / Egresos, ago-26) | B19: =Flujo_Caja!B26/Flujo_Caja!B80 -> 1.2095511 | E19: Flujo_Caja — sobre 1,0x el flujo operacional cubre el gasto; bajo 1,0x se financia con activos
A20: Meses de gasto cubiertos por Liquidez pura | B20: =Balance_Consolidado!B6/Flujo_Caja!B80 -> 1.2845286 | E20: Liquidez ÷ Egresos mensuales
A21: Peor Saldo Acumulado proyectado en los próximos 10 años | B21: =MIN(Flujo_Caja!E89:E92) -> -1442977982 | E21: Flujo_Caja, columna Saldo Acumulado — revisar causa si es negativo
A23: C. RENTABILIDAD Y CRECIMIENTO PROYECTADO — 1 / 5 / 10 AÑOS
A24: KPI | B24: 1 año | C24: 5 años | D24: 10 años | E24: Fórmula / Fuente
A25: Patrimonio Neto proyectado (aplicando retorno esperado ponderado) | B25: =$B$8*(1+ (Balance_Consolidado!B6/$B$6)*Supuestos!$B$10 + (Balance_Consolidado!B7/$B$6)*Supuestos!$B$11 + (Balance_Consolidado!B10/$B$6)*Supuestos!$B$12 + (Balance_Consolidado!B11/$B$6)*Supuestos!$B$13)^1 -> 1.5282259e+10 | C25: =$B$8*(1+ (Balance_Consolidado!B6/$B$6)*Supuestos!$B$10 + (Balance_Consolidado!B7/$B$6)*Supuestos!$B$11 + (Balance_Consolidado!B10/$B$6)*Supuestos!$B$12 + (Balance_Consolidado!B11/$B$6)*Supuestos!$B$13)^5 -> 1.8173196e+10 | D25: =$B$8*(1+ (Balance_Consolidado!B6/$B$6)*Supuestos!$B$10 + (Balance_Consolidado!B7/$B$6)*Supuestos!$B$11 + (Balance_Consolidado!B10/$B$6)*Supuestos!$B$12 + (Balance_Consolidado!B11/$B$6)*Supuestos!$B$13)^10 -> 2.2567633e+10 | E25: Retorno ponderado por peso de cada clase de activo × tasas de Supuestos. Requiere que Supuestos B9:B12 estén completos.
A26: CAGR implícito del patrimonio (retorno ponderado de Supuestos) | B26: =(Balance_Consolidado!B6/$B$6)*Supuestos!$B$10+(Balance_Consolidado!B7/$B$6)*Supuestos!$B$11+(Balance_Consolidado!B10/$B$6)*Supuestos!$B$12+(Balance_Consolidado!B11/$B$6)*Supuestos!$B$13 -> 0.044265516 | C26: =(Balance_Consolidado!B6/$B$6)*Supuestos!$B$10+(Balance_Consolidado!B7/$B$6)*Supuestos!$B$11+(Balance_Consolidado!B10/$B$6)*Supuestos!$B$12+(Balance_Consolidado!B11/$B$6)*Supuestos!$B$13 -> 0.044265516 | D26: =(Balance_Consolidado!B6/$B$6)*Supuestos!$B$10+(Balance_Consolidado!B7/$B$6)*Supuestos!$B$11+(Balance_Consolidado!B10/$B$6)*Supuestos!$B$12+(Balance_Consolidado!B11/$B$6)*Supuestos!$B$13 -> 0.044265516
A27: Ingresos operacionales proyectados (según modelo Flujo General) | B27: =Flujo_Caja!B90 -> 48290827 | C27: =Flujo_Caja!B91 -> 50494954 | D27: =Flujo_Caja!B92 -> 50757902
A28: Egresos operacionales proyectados (según modelo Flujo General) | B28: =Flujo_Caja!C90 -> 30357671 | C28: =Flujo_Caja!C91 -> 27634249 | D28: =Flujo_Caja!C92 -> 27395555
A30: D. RIESGO Y CONCENTRACIÓN
A31: KPI | B31: Valor | E31: Fórmula / Fuente
A32: Índice de concentración (HHI simplificado: suma de % al cuadrado por clase de activo) | B32: =(Balance_Consolidado!B6/$B$6)^2+(Balance_Consolidado!B7/$B$6)^2+(Balance_Consolidado!B10/$B$6)^2+(Balance_Consolidado!B11/$B$6)^2 -> 0.45147076 | E32: 1,0 = un solo activo concentra el 100%; mientras más cerca de 0,25 (=1/4 clases), más diversificado
A33: Activos Contingentes / Patrimonio Neto (riesgo de sobreestimación si se excluyen) | B33: =Balance_Consolidado!B21/B8 -> 0.012363681 | E33: Activos_Contingentes ÷ Patrimonio Neto
A34: Pasivos identificados con dueño no confirmado (FM Santander "DL") | B34: 834889277 | E34: Inversiones_Financieras — posición material sin titular confirmado, no ponderada en KPIs de riesgo hasta aclarar
